{"url":"http:\/\/kings.local\/perfil\/actualizar-juego\/6","method":"POST","isAJAX":false,"startTime":1749941889.934549,"totalTime":80.69999999999999,"totalMemory":"5.979","segmentDuration":15,"segmentCount":6,"CI_VERSION":"4.6.0","collectors":[{"title":"Timers","titleSafe":"timers","titleDetails":"","display":[],"badgeValue":null,"isEmpty":false,"hasTabContent":false,"hasLabel":false,"icon":"","hasTimelineData":true,"timelineData":[{"name":"Bootstrap","component":"Timer","start":1749941889.937133,"duration":0.014078855514526367},{"name":"Required Before Filters","component":"Timer","start":1749941889.951212,"duration":0.0020220279693603516},{"name":"Routing","component":"Timer","start":1749941889.953239,"duration":0.0005979537963867188},{"name":"Before Filters","component":"Timer","start":1749941889.954014,"duration":1.6927719116210938e-5},{"name":"Controller","component":"Timer","start":1749941889.954032,"duration":0.06082606315612793},{"name":"Controller Constructor","component":"Timer","start":1749941889.954033,"duration":0.006541013717651367},{"name":"After Filters","component":"Timer","start":1749941890.014871,"duration":5.0067901611328125e-6},{"name":"Required After Filters","component":"Timer","start":1749941890.014885,"duration":0.00040912628173828125}]},{"title":"Database","titleSafe":"database","titleDetails":"(17 total Queries, 17 of them unique across 1 Connection)","display":{"queries":[{"hover":"","class":"","duration":"2.6 ms","sql":"<strong>UPDATE<\/strong> `juegos` SET `title` = &#039;Cyberpunk 2077&#039;, `price` = &#039;29.99&#039;, `release_date` = &#039;2020-12-10&#039;, `developer` = &#039;CD Projekt RED&#039;, `rating` = &#039;8.0&#039;, `about` = &#039;Un RPG de mundo abierto ambientado en un futuro dist\u00f3pico lleno de acci\u00f3n, tecnolog\u00eda y decisiones.&#039;, `synopsis` = &#039;Cyberpunk 2077 transporta a los jugadores a Night City, una metr\u00f3polis obsesionada con el poder, la modificaci\u00f3n corporal y el estatus. Interpret\u00e1s a V, un mercenario en busca de un implante que puede otorgar la inmortalidad.\\r\\n\\r\\nA pesar de un lanzamiento pol\u00e9mico, el juego se ha pulido con el tiempo y ofrece una experiencia profunda, con una narrativa no lineal, m\u00faltiples finales y una ambientaci\u00f3n vibrante que da vida a un mundo cyberpunk como nunca antes.&#039;, `youtube_trailer_id` = &#039;8X2kIfS6fb8?si=pwOQQLVDsxTOdGv4&#039;, `cover_image_url` = &#039;https:\/\/cdn2.steamgriddb.com\/grid\/f39b781760a403dedaa05587e8889c1a.png&#039;, `card_image_url` = &#039;https:\/\/cdn2.steamgriddb.com\/grid\/796c4dde50f3fcea641e99ab0fb6dc70.jpg&#039;, `banner_image_url` = &#039;https:\/\/cdn2.steamgriddb.com\/hero\/fb87582825f9d28a8d42c5e5e5e8b23d.png&#039;, `logo_url` = &#039;https:\/\/cdn2.steamgriddb.com\/logo\/2b2e7393b05b5b52af65bf2ed7f4ad4f.png&#039;, `updated_at` = &#039;2025-06-14 22:58:09&#039;\n<strong>WHERE<\/strong> `juegos`.`game_id` <strong>IN<\/strong> (&#039;6&#039;)","trace":[{"file":"SYSTEMPATH\\Database\\BaseBuilder.php:2521","function":"\u00a0\u00a0\u00a0\u00a0\u00a0\u00a0\u00a0\u00a0CodeIgniter\\Database\\BaseConnection->query()","index":"\u00a0\u00a01\u00a0\u00a0\u00a0\u00a0"},{"file":"SYSTEMPATH\\Model.php:461","function":"\u00a0\u00a0\u00a0\u00a0\u00a0\u00a0\u00a0\u00a0CodeIgniter\\Database\\BaseBuilder->update()","index":"\u00a0\u00a02\u00a0\u00a0\u00a0\u00a0"},{"file":"SYSTEMPATH\\BaseModel.php:1027","function":"\u00a0\u00a0\u00a0\u00a0\u00a0\u00a0\u00a0\u00a0CodeIgniter\\Model->doUpdate()","index":"\u00a0\u00a03\u00a0\u00a0\u00a0\u00a0"},{"file":"SYSTEMPATH\\Model.php:863","function":"\u00a0\u00a0\u00a0\u00a0\u00a0\u00a0\u00a0\u00a0CodeIgniter\\BaseModel->update()","index":"\u00a0\u00a04\u00a0\u00a0\u00a0\u00a0"},{"file":"APPPATH\\Controllers\\Admin_controllers\\Admin.php:542","function":"\u00a0\u00a0\u00a0\u00a0\u00a0\u00a0\u00a0\u00a0CodeIgniter\\Model->update()","index":"\u00a0\u00a05\u00a0\u00a0\u00a0\u00a0"},{"file":"SYSTEMPATH\\CodeIgniter.php:933","function":"\u00a0\u00a0\u00a0\u00a0\u00a0\u00a0\u00a0\u00a0App\\Controllers\\Admin_controllers\\Admin->actualizar_juego()","index":"\u00a0\u00a06\u00a0\u00a0\u00a0\u00a0"},{"file":"SYSTEMPATH\\CodeIgniter.php:507","function":"\u00a0\u00a0\u00a0\u00a0\u00a0\u00a0\u00a0\u00a0CodeIgniter\\CodeIgniter->runController()","index":"\u00a0\u00a07\u00a0\u00a0\u00a0\u00a0"},{"file":"SYSTEMPATH\\CodeIgniter.php:354","function":"\u00a0\u00a0\u00a0\u00a0\u00a0\u00a0\u00a0\u00a0CodeIgniter\\CodeIgniter->handleRequest()","index":"\u00a0\u00a08\u00a0\u00a0\u00a0\u00a0"},{"file":"SYSTEMPATH\\Boot.php:334","function":"\u00a0\u00a0\u00a0\u00a0\u00a0\u00a0\u00a0\u00a0CodeIgniter\\CodeIgniter->run()","index":"\u00a0\u00a09\u00a0\u00a0\u00a0\u00a0"},{"file":"SYSTEMPATH\\Boot.php:67","function":"\u00a0\u00a0\u00a0\u00a0\u00a0\u00a0\u00a0\u00a0CodeIgniter\\Boot::runCodeIgniter()","index":"\u00a010\u00a0\u00a0\u00a0\u00a0"},{"file":"FCPATH\\index.php:59","function":"\u00a0\u00a0\u00a0\u00a0\u00a0\u00a0\u00a0\u00a0CodeIgniter\\Boot::bootWeb()","index":"\u00a011\u00a0\u00a0\u00a0\u00a0"}],"trace-file":"APPPATH\\Controllers\\Admin_controllers\\Admin.php:542","qid":"371960872b90923149370a3eae37547d"},{"hover":"","class":"","duration":"2.22 ms","sql":"DELETE <strong>FROM<\/strong> `juego_categorias`\n<strong>WHERE<\/strong> `game_id` = &#039;6&#039;","trace":[{"file":"SYSTEMPATH\\Database\\BaseBuilder.php:2848","function":"\u00a0\u00a0\u00a0\u00a0\u00a0\u00a0\u00a0\u00a0CodeIgniter\\Database\\BaseConnection->query()","index":"\u00a0\u00a01\u00a0\u00a0\u00a0\u00a0"},{"file":"SYSTEMPATH\\Model.php:521","function":"\u00a0\u00a0\u00a0\u00a0\u00a0\u00a0\u00a0\u00a0CodeIgniter\\Database\\BaseBuilder->delete()","index":"\u00a0\u00a02\u00a0\u00a0\u00a0\u00a0"},{"file":"SYSTEMPATH\\BaseModel.php:1157","function":"\u00a0\u00a0\u00a0\u00a0\u00a0\u00a0\u00a0\u00a0CodeIgniter\\Model->doDelete()","index":"\u00a0\u00a03\u00a0\u00a0\u00a0\u00a0"},{"file":"APPPATH\\Controllers\\Admin_controllers\\Admin.php:545","function":"\u00a0\u00a0\u00a0\u00a0\u00a0\u00a0\u00a0\u00a0CodeIgniter\\BaseModel->delete()","index":"\u00a0\u00a04\u00a0\u00a0\u00a0\u00a0"},{"file":"SYSTEMPATH\\CodeIgniter.php:933","function":"\u00a0\u00a0\u00a0\u00a0\u00a0\u00a0\u00a0\u00a0App\\Controllers\\Admin_controllers\\Admin->actualizar_juego()","index":"\u00a0\u00a05\u00a0\u00a0\u00a0\u00a0"},{"file":"SYSTEMPATH\\CodeIgniter.php:507","function":"\u00a0\u00a0\u00a0\u00a0\u00a0\u00a0\u00a0\u00a0CodeIgniter\\CodeIgniter->runController()","index":"\u00a0\u00a06\u00a0\u00a0\u00a0\u00a0"},{"file":"SYSTEMPATH\\CodeIgniter.php:354","function":"\u00a0\u00a0\u00a0\u00a0\u00a0\u00a0\u00a0\u00a0CodeIgniter\\CodeIgniter->handleRequest()","index":"\u00a0\u00a07\u00a0\u00a0\u00a0\u00a0"},{"file":"SYSTEMPATH\\Boot.php:334","function":"\u00a0\u00a0\u00a0\u00a0\u00a0\u00a0\u00a0\u00a0CodeIgniter\\CodeIgniter->run()","index":"\u00a0\u00a08\u00a0\u00a0\u00a0\u00a0"},{"file":"SYSTEMPATH\\Boot.php:67","function":"\u00a0\u00a0\u00a0\u00a0\u00a0\u00a0\u00a0\u00a0CodeIgniter\\Boot::runCodeIgniter()","index":"\u00a0\u00a09\u00a0\u00a0\u00a0\u00a0"},{"file":"FCPATH\\index.php:59","function":"\u00a0\u00a0\u00a0\u00a0\u00a0\u00a0\u00a0\u00a0CodeIgniter\\Boot::bootWeb()","index":"\u00a010\u00a0\u00a0\u00a0\u00a0"}],"trace-file":"APPPATH\\Controllers\\Admin_controllers\\Admin.php:545","qid":"1ba946b731b306dc302328257e0b6ae0"},{"hover":"","class":"","duration":"2.21 ms","sql":"<strong>INSERT<\/strong> <strong>INTO<\/strong> `juego_categorias` (`game_id`, `category_id`) <strong>VALUES<\/strong> (&#039;6&#039;, &#039;1&#039;)","trace":[{"file":"SYSTEMPATH\\Database\\BaseBuilder.php:2345","function":"\u00a0\u00a0\u00a0\u00a0\u00a0\u00a0\u00a0\u00a0CodeIgniter\\Database\\BaseConnection->query()","index":"\u00a0\u00a01\u00a0\u00a0\u00a0\u00a0"},{"file":"SYSTEMPATH\\Model.php:394","function":"\u00a0\u00a0\u00a0\u00a0\u00a0\u00a0\u00a0\u00a0CodeIgniter\\Database\\BaseBuilder->insert()","index":"\u00a0\u00a02\u00a0\u00a0\u00a0\u00a0"},{"file":"SYSTEMPATH\\BaseModel.php:839","function":"\u00a0\u00a0\u00a0\u00a0\u00a0\u00a0\u00a0\u00a0CodeIgniter\\Model->doInsert()","index":"\u00a0\u00a03\u00a0\u00a0\u00a0\u00a0"},{"file":"SYSTEMPATH\\Model.php:800","function":"\u00a0\u00a0\u00a0\u00a0\u00a0\u00a0\u00a0\u00a0CodeIgniter\\BaseModel->insert()","index":"\u00a0\u00a04\u00a0\u00a0\u00a0\u00a0"},{"file":"APPPATH\\Controllers\\Admin_controllers\\Admin.php:549","function":"\u00a0\u00a0\u00a0\u00a0\u00a0\u00a0\u00a0\u00a0CodeIgniter\\Model->insert()","index":"\u00a0\u00a05\u00a0\u00a0\u00a0\u00a0"},{"file":"SYSTEMPATH\\CodeIgniter.php:933","function":"\u00a0\u00a0\u00a0\u00a0\u00a0\u00a0\u00a0\u00a0App\\Controllers\\Admin_controllers\\Admin->actualizar_juego()","index":"\u00a0\u00a06\u00a0\u00a0\u00a0\u00a0"},{"file":"SYSTEMPATH\\CodeIgniter.php:507","function":"\u00a0\u00a0\u00a0\u00a0\u00a0\u00a0\u00a0\u00a0CodeIgniter\\CodeIgniter->runController()","index":"\u00a0\u00a07\u00a0\u00a0\u00a0\u00a0"},{"file":"SYSTEMPATH\\CodeIgniter.php:354","function":"\u00a0\u00a0\u00a0\u00a0\u00a0\u00a0\u00a0\u00a0CodeIgniter\\CodeIgniter->handleRequest()","index":"\u00a0\u00a08\u00a0\u00a0\u00a0\u00a0"},{"file":"SYSTEMPATH\\Boot.php:334","function":"\u00a0\u00a0\u00a0\u00a0\u00a0\u00a0\u00a0\u00a0CodeIgniter\\CodeIgniter->run()","index":"\u00a0\u00a09\u00a0\u00a0\u00a0\u00a0"},{"file":"SYSTEMPATH\\Boot.php:67","function":"\u00a0\u00a0\u00a0\u00a0\u00a0\u00a0\u00a0\u00a0CodeIgniter\\Boot::runCodeIgniter()","index":"\u00a010\u00a0\u00a0\u00a0\u00a0"},{"file":"FCPATH\\index.php:59","function":"\u00a0\u00a0\u00a0\u00a0\u00a0\u00a0\u00a0\u00a0CodeIgniter\\Boot::bootWeb()","index":"\u00a011\u00a0\u00a0\u00a0\u00a0"}],"trace-file":"APPPATH\\Controllers\\Admin_controllers\\Admin.php:549","qid":"603f6cd9bb1ff0abcfc2ca1eab4f6d47"},{"hover":"","class":"","duration":"2.41 ms","sql":"<strong>INSERT<\/strong> <strong>INTO<\/strong> `juego_categorias` (`game_id`, `category_id`) <strong>VALUES<\/strong> (&#039;6&#039;, &#039;2&#039;)","trace":[{"file":"SYSTEMPATH\\Database\\BaseBuilder.php:2345","function":"\u00a0\u00a0\u00a0\u00a0\u00a0\u00a0\u00a0\u00a0CodeIgniter\\Database\\BaseConnection->query()","index":"\u00a0\u00a01\u00a0\u00a0\u00a0\u00a0"},{"file":"SYSTEMPATH\\Model.php:394","function":"\u00a0\u00a0\u00a0\u00a0\u00a0\u00a0\u00a0\u00a0CodeIgniter\\Database\\BaseBuilder->insert()","index":"\u00a0\u00a02\u00a0\u00a0\u00a0\u00a0"},{"file":"SYSTEMPATH\\BaseModel.php:839","function":"\u00a0\u00a0\u00a0\u00a0\u00a0\u00a0\u00a0\u00a0CodeIgniter\\Model->doInsert()","index":"\u00a0\u00a03\u00a0\u00a0\u00a0\u00a0"},{"file":"SYSTEMPATH\\Model.php:800","function":"\u00a0\u00a0\u00a0\u00a0\u00a0\u00a0\u00a0\u00a0CodeIgniter\\BaseModel->insert()","index":"\u00a0\u00a04\u00a0\u00a0\u00a0\u00a0"},{"file":"APPPATH\\Controllers\\Admin_controllers\\Admin.php:549","function":"\u00a0\u00a0\u00a0\u00a0\u00a0\u00a0\u00a0\u00a0CodeIgniter\\Model->insert()","index":"\u00a0\u00a05\u00a0\u00a0\u00a0\u00a0"},{"file":"SYSTEMPATH\\CodeIgniter.php:933","function":"\u00a0\u00a0\u00a0\u00a0\u00a0\u00a0\u00a0\u00a0App\\Controllers\\Admin_controllers\\Admin->actualizar_juego()","index":"\u00a0\u00a06\u00a0\u00a0\u00a0\u00a0"},{"file":"SYSTEMPATH\\CodeIgniter.php:507","function":"\u00a0\u00a0\u00a0\u00a0\u00a0\u00a0\u00a0\u00a0CodeIgniter\\CodeIgniter->runController()","index":"\u00a0\u00a07\u00a0\u00a0\u00a0\u00a0"},{"file":"SYSTEMPATH\\CodeIgniter.php:354","function":"\u00a0\u00a0\u00a0\u00a0\u00a0\u00a0\u00a0\u00a0CodeIgniter\\CodeIgniter->handleRequest()","index":"\u00a0\u00a08\u00a0\u00a0\u00a0\u00a0"},{"file":"SYSTEMPATH\\Boot.php:334","function":"\u00a0\u00a0\u00a0\u00a0\u00a0\u00a0\u00a0\u00a0CodeIgniter\\CodeIgniter->run()","index":"\u00a0\u00a09\u00a0\u00a0\u00a0\u00a0"},{"file":"SYSTEMPATH\\Boot.php:67","function":"\u00a0\u00a0\u00a0\u00a0\u00a0\u00a0\u00a0\u00a0CodeIgniter\\Boot::runCodeIgniter()","index":"\u00a010\u00a0\u00a0\u00a0\u00a0"},{"file":"FCPATH\\index.php:59","function":"\u00a0\u00a0\u00a0\u00a0\u00a0\u00a0\u00a0\u00a0CodeIgniter\\Boot::bootWeb()","index":"\u00a011\u00a0\u00a0\u00a0\u00a0"}],"trace-file":"APPPATH\\Controllers\\Admin_controllers\\Admin.php:549","qid":"5486c8b41fc858a9f24b0cb4ac0fd7cf"},{"hover":"","class":"","duration":"2.2 ms","sql":"<strong>INSERT<\/strong> <strong>INTO<\/strong> `juego_categorias` (`game_id`, `category_id`) <strong>VALUES<\/strong> (&#039;6&#039;, &#039;7&#039;)","trace":[{"file":"SYSTEMPATH\\Database\\BaseBuilder.php:2345","function":"\u00a0\u00a0\u00a0\u00a0\u00a0\u00a0\u00a0\u00a0CodeIgniter\\Database\\BaseConnection->query()","index":"\u00a0\u00a01\u00a0\u00a0\u00a0\u00a0"},{"file":"SYSTEMPATH\\Model.php:394","function":"\u00a0\u00a0\u00a0\u00a0\u00a0\u00a0\u00a0\u00a0CodeIgniter\\Database\\BaseBuilder->insert()","index":"\u00a0\u00a02\u00a0\u00a0\u00a0\u00a0"},{"file":"SYSTEMPATH\\BaseModel.php:839","function":"\u00a0\u00a0\u00a0\u00a0\u00a0\u00a0\u00a0\u00a0CodeIgniter\\Model->doInsert()","index":"\u00a0\u00a03\u00a0\u00a0\u00a0\u00a0"},{"file":"SYSTEMPATH\\Model.php:800","function":"\u00a0\u00a0\u00a0\u00a0\u00a0\u00a0\u00a0\u00a0CodeIgniter\\BaseModel->insert()","index":"\u00a0\u00a04\u00a0\u00a0\u00a0\u00a0"},{"file":"APPPATH\\Controllers\\Admin_controllers\\Admin.php:549","function":"\u00a0\u00a0\u00a0\u00a0\u00a0\u00a0\u00a0\u00a0CodeIgniter\\Model->insert()","index":"\u00a0\u00a05\u00a0\u00a0\u00a0\u00a0"},{"file":"SYSTEMPATH\\CodeIgniter.php:933","function":"\u00a0\u00a0\u00a0\u00a0\u00a0\u00a0\u00a0\u00a0App\\Controllers\\Admin_controllers\\Admin->actualizar_juego()","index":"\u00a0\u00a06\u00a0\u00a0\u00a0\u00a0"},{"file":"SYSTEMPATH\\CodeIgniter.php:507","function":"\u00a0\u00a0\u00a0\u00a0\u00a0\u00a0\u00a0\u00a0CodeIgniter\\CodeIgniter->runController()","index":"\u00a0\u00a07\u00a0\u00a0\u00a0\u00a0"},{"file":"SYSTEMPATH\\CodeIgniter.php:354","function":"\u00a0\u00a0\u00a0\u00a0\u00a0\u00a0\u00a0\u00a0CodeIgniter\\CodeIgniter->handleRequest()","index":"\u00a0\u00a08\u00a0\u00a0\u00a0\u00a0"},{"file":"SYSTEMPATH\\Boot.php:334","function":"\u00a0\u00a0\u00a0\u00a0\u00a0\u00a0\u00a0\u00a0CodeIgniter\\CodeIgniter->run()","index":"\u00a0\u00a09\u00a0\u00a0\u00a0\u00a0"},{"file":"SYSTEMPATH\\Boot.php:67","function":"\u00a0\u00a0\u00a0\u00a0\u00a0\u00a0\u00a0\u00a0CodeIgniter\\Boot::runCodeIgniter()","index":"\u00a010\u00a0\u00a0\u00a0\u00a0"},{"file":"FCPATH\\index.php:59","function":"\u00a0\u00a0\u00a0\u00a0\u00a0\u00a0\u00a0\u00a0CodeIgniter\\Boot::bootWeb()","index":"\u00a011\u00a0\u00a0\u00a0\u00a0"}],"trace-file":"APPPATH\\Controllers\\Admin_controllers\\Admin.php:549","qid":"b4b51192bd8a16c17f5cad65c8246dff"},{"hover":"","class":"","duration":"2.18 ms","sql":"<strong>INSERT<\/strong> <strong>INTO<\/strong> `juego_categorias` (`game_id`, `category_id`) <strong>VALUES<\/strong> (&#039;6&#039;, &#039;9&#039;)","trace":[{"file":"SYSTEMPATH\\Database\\BaseBuilder.php:2345","function":"\u00a0\u00a0\u00a0\u00a0\u00a0\u00a0\u00a0\u00a0CodeIgniter\\Database\\BaseConnection->query()","index":"\u00a0\u00a01\u00a0\u00a0\u00a0\u00a0"},{"file":"SYSTEMPATH\\Model.php:394","function":"\u00a0\u00a0\u00a0\u00a0\u00a0\u00a0\u00a0\u00a0CodeIgniter\\Database\\BaseBuilder->insert()","index":"\u00a0\u00a02\u00a0\u00a0\u00a0\u00a0"},{"file":"SYSTEMPATH\\BaseModel.php:839","function":"\u00a0\u00a0\u00a0\u00a0\u00a0\u00a0\u00a0\u00a0CodeIgniter\\Model->doInsert()","index":"\u00a0\u00a03\u00a0\u00a0\u00a0\u00a0"},{"file":"SYSTEMPATH\\Model.php:800","function":"\u00a0\u00a0\u00a0\u00a0\u00a0\u00a0\u00a0\u00a0CodeIgniter\\BaseModel->insert()","index":"\u00a0\u00a04\u00a0\u00a0\u00a0\u00a0"},{"file":"APPPATH\\Controllers\\Admin_controllers\\Admin.php:549","function":"\u00a0\u00a0\u00a0\u00a0\u00a0\u00a0\u00a0\u00a0CodeIgniter\\Model->insert()","index":"\u00a0\u00a05\u00a0\u00a0\u00a0\u00a0"},{"file":"SYSTEMPATH\\CodeIgniter.php:933","function":"\u00a0\u00a0\u00a0\u00a0\u00a0\u00a0\u00a0\u00a0App\\Controllers\\Admin_controllers\\Admin->actualizar_juego()","index":"\u00a0\u00a06\u00a0\u00a0\u00a0\u00a0"},{"file":"SYSTEMPATH\\CodeIgniter.php:507","function":"\u00a0\u00a0\u00a0\u00a0\u00a0\u00a0\u00a0\u00a0CodeIgniter\\CodeIgniter->runController()","index":"\u00a0\u00a07\u00a0\u00a0\u00a0\u00a0"},{"file":"SYSTEMPATH\\CodeIgniter.php:354","function":"\u00a0\u00a0\u00a0\u00a0\u00a0\u00a0\u00a0\u00a0CodeIgniter\\CodeIgniter->handleRequest()","index":"\u00a0\u00a08\u00a0\u00a0\u00a0\u00a0"},{"file":"SYSTEMPATH\\Boot.php:334","function":"\u00a0\u00a0\u00a0\u00a0\u00a0\u00a0\u00a0\u00a0CodeIgniter\\CodeIgniter->run()","index":"\u00a0\u00a09\u00a0\u00a0\u00a0\u00a0"},{"file":"SYSTEMPATH\\Boot.php:67","function":"\u00a0\u00a0\u00a0\u00a0\u00a0\u00a0\u00a0\u00a0CodeIgniter\\Boot::runCodeIgniter()","index":"\u00a010\u00a0\u00a0\u00a0\u00a0"},{"file":"FCPATH\\index.php:59","function":"\u00a0\u00a0\u00a0\u00a0\u00a0\u00a0\u00a0\u00a0CodeIgniter\\Boot::bootWeb()","index":"\u00a011\u00a0\u00a0\u00a0\u00a0"}],"trace-file":"APPPATH\\Controllers\\Admin_controllers\\Admin.php:549","qid":"29136b82989586e9adb2de59eb42e319"},{"hover":"","class":"","duration":"2.18 ms","sql":"<strong>INSERT<\/strong> <strong>INTO<\/strong> `juego_categorias` (`game_id`, `category_id`) <strong>VALUES<\/strong> (&#039;6&#039;, &#039;10&#039;)","trace":[{"file":"SYSTEMPATH\\Database\\BaseBuilder.php:2345","function":"\u00a0\u00a0\u00a0\u00a0\u00a0\u00a0\u00a0\u00a0CodeIgniter\\Database\\BaseConnection->query()","index":"\u00a0\u00a01\u00a0\u00a0\u00a0\u00a0"},{"file":"SYSTEMPATH\\Model.php:394","function":"\u00a0\u00a0\u00a0\u00a0\u00a0\u00a0\u00a0\u00a0CodeIgniter\\Database\\BaseBuilder->insert()","index":"\u00a0\u00a02\u00a0\u00a0\u00a0\u00a0"},{"file":"SYSTEMPATH\\BaseModel.php:839","function":"\u00a0\u00a0\u00a0\u00a0\u00a0\u00a0\u00a0\u00a0CodeIgniter\\Model->doInsert()","index":"\u00a0\u00a03\u00a0\u00a0\u00a0\u00a0"},{"file":"SYSTEMPATH\\Model.php:800","function":"\u00a0\u00a0\u00a0\u00a0\u00a0\u00a0\u00a0\u00a0CodeIgniter\\BaseModel->insert()","index":"\u00a0\u00a04\u00a0\u00a0\u00a0\u00a0"},{"file":"APPPATH\\Controllers\\Admin_controllers\\Admin.php:549","function":"\u00a0\u00a0\u00a0\u00a0\u00a0\u00a0\u00a0\u00a0CodeIgniter\\Model->insert()","index":"\u00a0\u00a05\u00a0\u00a0\u00a0\u00a0"},{"file":"SYSTEMPATH\\CodeIgniter.php:933","function":"\u00a0\u00a0\u00a0\u00a0\u00a0\u00a0\u00a0\u00a0App\\Controllers\\Admin_controllers\\Admin->actualizar_juego()","index":"\u00a0\u00a06\u00a0\u00a0\u00a0\u00a0"},{"file":"SYSTEMPATH\\CodeIgniter.php:507","function":"\u00a0\u00a0\u00a0\u00a0\u00a0\u00a0\u00a0\u00a0CodeIgniter\\CodeIgniter->runController()","index":"\u00a0\u00a07\u00a0\u00a0\u00a0\u00a0"},{"file":"SYSTEMPATH\\CodeIgniter.php:354","function":"\u00a0\u00a0\u00a0\u00a0\u00a0\u00a0\u00a0\u00a0CodeIgniter\\CodeIgniter->handleRequest()","index":"\u00a0\u00a08\u00a0\u00a0\u00a0\u00a0"},{"file":"SYSTEMPATH\\Boot.php:334","function":"\u00a0\u00a0\u00a0\u00a0\u00a0\u00a0\u00a0\u00a0CodeIgniter\\CodeIgniter->run()","index":"\u00a0\u00a09\u00a0\u00a0\u00a0\u00a0"},{"file":"SYSTEMPATH\\Boot.php:67","function":"\u00a0\u00a0\u00a0\u00a0\u00a0\u00a0\u00a0\u00a0CodeIgniter\\Boot::runCodeIgniter()","index":"\u00a010\u00a0\u00a0\u00a0\u00a0"},{"file":"FCPATH\\index.php:59","function":"\u00a0\u00a0\u00a0\u00a0\u00a0\u00a0\u00a0\u00a0CodeIgniter\\Boot::bootWeb()","index":"\u00a011\u00a0\u00a0\u00a0\u00a0"}],"trace-file":"APPPATH\\Controllers\\Admin_controllers\\Admin.php:549","qid":"d13202d0fab76c77751d923fea5d1eff"},{"hover":"","class":"","duration":"2.35 ms","sql":"<strong>INSERT<\/strong> <strong>INTO<\/strong> `juego_categorias` (`game_id`, `category_id`) <strong>VALUES<\/strong> (&#039;6&#039;, &#039;11&#039;)","trace":[{"file":"SYSTEMPATH\\Database\\BaseBuilder.php:2345","function":"\u00a0\u00a0\u00a0\u00a0\u00a0\u00a0\u00a0\u00a0CodeIgniter\\Database\\BaseConnection->query()","index":"\u00a0\u00a01\u00a0\u00a0\u00a0\u00a0"},{"file":"SYSTEMPATH\\Model.php:394","function":"\u00a0\u00a0\u00a0\u00a0\u00a0\u00a0\u00a0\u00a0CodeIgniter\\Database\\BaseBuilder->insert()","index":"\u00a0\u00a02\u00a0\u00a0\u00a0\u00a0"},{"file":"SYSTEMPATH\\BaseModel.php:839","function":"\u00a0\u00a0\u00a0\u00a0\u00a0\u00a0\u00a0\u00a0CodeIgniter\\Model->doInsert()","index":"\u00a0\u00a03\u00a0\u00a0\u00a0\u00a0"},{"file":"SYSTEMPATH\\Model.php:800","function":"\u00a0\u00a0\u00a0\u00a0\u00a0\u00a0\u00a0\u00a0CodeIgniter\\BaseModel->insert()","index":"\u00a0\u00a04\u00a0\u00a0\u00a0\u00a0"},{"file":"APPPATH\\Controllers\\Admin_controllers\\Admin.php:549","function":"\u00a0\u00a0\u00a0\u00a0\u00a0\u00a0\u00a0\u00a0CodeIgniter\\Model->insert()","index":"\u00a0\u00a05\u00a0\u00a0\u00a0\u00a0"},{"file":"SYSTEMPATH\\CodeIgniter.php:933","function":"\u00a0\u00a0\u00a0\u00a0\u00a0\u00a0\u00a0\u00a0App\\Controllers\\Admin_controllers\\Admin->actualizar_juego()","index":"\u00a0\u00a06\u00a0\u00a0\u00a0\u00a0"},{"file":"SYSTEMPATH\\CodeIgniter.php:507","function":"\u00a0\u00a0\u00a0\u00a0\u00a0\u00a0\u00a0\u00a0CodeIgniter\\CodeIgniter->runController()","index":"\u00a0\u00a07\u00a0\u00a0\u00a0\u00a0"},{"file":"SYSTEMPATH\\CodeIgniter.php:354","function":"\u00a0\u00a0\u00a0\u00a0\u00a0\u00a0\u00a0\u00a0CodeIgniter\\CodeIgniter->handleRequest()","index":"\u00a0\u00a08\u00a0\u00a0\u00a0\u00a0"},{"file":"SYSTEMPATH\\Boot.php:334","function":"\u00a0\u00a0\u00a0\u00a0\u00a0\u00a0\u00a0\u00a0CodeIgniter\\CodeIgniter->run()","index":"\u00a0\u00a09\u00a0\u00a0\u00a0\u00a0"},{"file":"SYSTEMPATH\\Boot.php:67","function":"\u00a0\u00a0\u00a0\u00a0\u00a0\u00a0\u00a0\u00a0CodeIgniter\\Boot::runCodeIgniter()","index":"\u00a010\u00a0\u00a0\u00a0\u00a0"},{"file":"FCPATH\\index.php:59","function":"\u00a0\u00a0\u00a0\u00a0\u00a0\u00a0\u00a0\u00a0CodeIgniter\\Boot::bootWeb()","index":"\u00a011\u00a0\u00a0\u00a0\u00a0"}],"trace-file":"APPPATH\\Controllers\\Admin_controllers\\Admin.php:549","qid":"ccdf9974accbcc7fae9e64216f1db9d5"},{"hover":"","class":"","duration":"2.21 ms","sql":"DELETE <strong>FROM<\/strong> `juegos_galeria`\n<strong>WHERE<\/strong> `game_id` = &#039;6&#039;","trace":[{"file":"SYSTEMPATH\\Database\\BaseBuilder.php:2848","function":"\u00a0\u00a0\u00a0\u00a0\u00a0\u00a0\u00a0\u00a0CodeIgniter\\Database\\BaseConnection->query()","index":"\u00a0\u00a01\u00a0\u00a0\u00a0\u00a0"},{"file":"SYSTEMPATH\\Model.php:521","function":"\u00a0\u00a0\u00a0\u00a0\u00a0\u00a0\u00a0\u00a0CodeIgniter\\Database\\BaseBuilder->delete()","index":"\u00a0\u00a02\u00a0\u00a0\u00a0\u00a0"},{"file":"SYSTEMPATH\\BaseModel.php:1157","function":"\u00a0\u00a0\u00a0\u00a0\u00a0\u00a0\u00a0\u00a0CodeIgniter\\Model->doDelete()","index":"\u00a0\u00a03\u00a0\u00a0\u00a0\u00a0"},{"file":"APPPATH\\Controllers\\Admin_controllers\\Admin.php:557","function":"\u00a0\u00a0\u00a0\u00a0\u00a0\u00a0\u00a0\u00a0CodeIgniter\\BaseModel->delete()","index":"\u00a0\u00a04\u00a0\u00a0\u00a0\u00a0"},{"file":"SYSTEMPATH\\CodeIgniter.php:933","function":"\u00a0\u00a0\u00a0\u00a0\u00a0\u00a0\u00a0\u00a0App\\Controllers\\Admin_controllers\\Admin->actualizar_juego()","index":"\u00a0\u00a05\u00a0\u00a0\u00a0\u00a0"},{"file":"SYSTEMPATH\\CodeIgniter.php:507","function":"\u00a0\u00a0\u00a0\u00a0\u00a0\u00a0\u00a0\u00a0CodeIgniter\\CodeIgniter->runController()","index":"\u00a0\u00a06\u00a0\u00a0\u00a0\u00a0"},{"file":"SYSTEMPATH\\CodeIgniter.php:354","function":"\u00a0\u00a0\u00a0\u00a0\u00a0\u00a0\u00a0\u00a0CodeIgniter\\CodeIgniter->handleRequest()","index":"\u00a0\u00a07\u00a0\u00a0\u00a0\u00a0"},{"file":"SYSTEMPATH\\Boot.php:334","function":"\u00a0\u00a0\u00a0\u00a0\u00a0\u00a0\u00a0\u00a0CodeIgniter\\CodeIgniter->run()","index":"\u00a0\u00a08\u00a0\u00a0\u00a0\u00a0"},{"file":"SYSTEMPATH\\Boot.php:67","function":"\u00a0\u00a0\u00a0\u00a0\u00a0\u00a0\u00a0\u00a0CodeIgniter\\Boot::runCodeIgniter()","index":"\u00a0\u00a09\u00a0\u00a0\u00a0\u00a0"},{"file":"FCPATH\\index.php:59","function":"\u00a0\u00a0\u00a0\u00a0\u00a0\u00a0\u00a0\u00a0CodeIgniter\\Boot::bootWeb()","index":"\u00a010\u00a0\u00a0\u00a0\u00a0"}],"trace-file":"APPPATH\\Controllers\\Admin_controllers\\Admin.php:557","qid":"0efb30ddfac896e1e10cf7ff408cf906"},{"hover":"","class":"","duration":"2.66 ms","sql":"<strong>INSERT<\/strong> <strong>INTO<\/strong> `juegos_galeria` (`game_id`, `image_url`) <strong>VALUES<\/strong> (&#039;6&#039;, &#039;https:\/\/shared.fastly.steamstatic.com\/store_item_assets\/steam\/apps\/1091500\/ss_7924f64b6e5d586a80418c9896a1c92881a7905b.1920x1080.jpg?t=1746519355&#039;)","trace":[{"file":"SYSTEMPATH\\Database\\BaseBuilder.php:2345","function":"\u00a0\u00a0\u00a0\u00a0\u00a0\u00a0\u00a0\u00a0CodeIgniter\\Database\\BaseConnection->query()","index":"\u00a0\u00a01\u00a0\u00a0\u00a0\u00a0"},{"file":"SYSTEMPATH\\Model.php:394","function":"\u00a0\u00a0\u00a0\u00a0\u00a0\u00a0\u00a0\u00a0CodeIgniter\\Database\\BaseBuilder->insert()","index":"\u00a0\u00a02\u00a0\u00a0\u00a0\u00a0"},{"file":"SYSTEMPATH\\BaseModel.php:839","function":"\u00a0\u00a0\u00a0\u00a0\u00a0\u00a0\u00a0\u00a0CodeIgniter\\Model->doInsert()","index":"\u00a0\u00a03\u00a0\u00a0\u00a0\u00a0"},{"file":"SYSTEMPATH\\Model.php:800","function":"\u00a0\u00a0\u00a0\u00a0\u00a0\u00a0\u00a0\u00a0CodeIgniter\\BaseModel->insert()","index":"\u00a0\u00a04\u00a0\u00a0\u00a0\u00a0"},{"file":"APPPATH\\Controllers\\Admin_controllers\\Admin.php:561","function":"\u00a0\u00a0\u00a0\u00a0\u00a0\u00a0\u00a0\u00a0CodeIgniter\\Model->insert()","index":"\u00a0\u00a05\u00a0\u00a0\u00a0\u00a0"},{"file":"SYSTEMPATH\\CodeIgniter.php:933","function":"\u00a0\u00a0\u00a0\u00a0\u00a0\u00a0\u00a0\u00a0App\\Controllers\\Admin_controllers\\Admin->actualizar_juego()","index":"\u00a0\u00a06\u00a0\u00a0\u00a0\u00a0"},{"file":"SYSTEMPATH\\CodeIgniter.php:507","function":"\u00a0\u00a0\u00a0\u00a0\u00a0\u00a0\u00a0\u00a0CodeIgniter\\CodeIgniter->runController()","index":"\u00a0\u00a07\u00a0\u00a0\u00a0\u00a0"},{"file":"SYSTEMPATH\\CodeIgniter.php:354","function":"\u00a0\u00a0\u00a0\u00a0\u00a0\u00a0\u00a0\u00a0CodeIgniter\\CodeIgniter->handleRequest()","index":"\u00a0\u00a08\u00a0\u00a0\u00a0\u00a0"},{"file":"SYSTEMPATH\\Boot.php:334","function":"\u00a0\u00a0\u00a0\u00a0\u00a0\u00a0\u00a0\u00a0CodeIgniter\\CodeIgniter->run()","index":"\u00a0\u00a09\u00a0\u00a0\u00a0\u00a0"},{"file":"SYSTEMPATH\\Boot.php:67","function":"\u00a0\u00a0\u00a0\u00a0\u00a0\u00a0\u00a0\u00a0CodeIgniter\\Boot::runCodeIgniter()","index":"\u00a010\u00a0\u00a0\u00a0\u00a0"},{"file":"FCPATH\\index.php:59","function":"\u00a0\u00a0\u00a0\u00a0\u00a0\u00a0\u00a0\u00a0CodeIgniter\\Boot::bootWeb()","index":"\u00a011\u00a0\u00a0\u00a0\u00a0"}],"trace-file":"APPPATH\\Controllers\\Admin_controllers\\Admin.php:561","qid":"78fc2c74c623a8d260002d634a95b912"},{"hover":"","class":"","duration":"2.41 ms","sql":"<strong>INSERT<\/strong> <strong>INTO<\/strong> `juegos_galeria` (`game_id`, `image_url`) <strong>VALUES<\/strong> (&#039;6&#039;, &#039;https:\/\/shared.fastly.steamstatic.com\/store_item_assets\/steam\/apps\/1091500\/ss_b529b0abc43f55fc23fe8058eddb6e37c9629a6a.1920x1080.jpg?t=1746519355&#039;)","trace":[{"file":"SYSTEMPATH\\Database\\BaseBuilder.php:2345","function":"\u00a0\u00a0\u00a0\u00a0\u00a0\u00a0\u00a0\u00a0CodeIgniter\\Database\\BaseConnection->query()","index":"\u00a0\u00a01\u00a0\u00a0\u00a0\u00a0"},{"file":"SYSTEMPATH\\Model.php:394","function":"\u00a0\u00a0\u00a0\u00a0\u00a0\u00a0\u00a0\u00a0CodeIgniter\\Database\\BaseBuilder->insert()","index":"\u00a0\u00a02\u00a0\u00a0\u00a0\u00a0"},{"file":"SYSTEMPATH\\BaseModel.php:839","function":"\u00a0\u00a0\u00a0\u00a0\u00a0\u00a0\u00a0\u00a0CodeIgniter\\Model->doInsert()","index":"\u00a0\u00a03\u00a0\u00a0\u00a0\u00a0"},{"file":"SYSTEMPATH\\Model.php:800","function":"\u00a0\u00a0\u00a0\u00a0\u00a0\u00a0\u00a0\u00a0CodeIgniter\\BaseModel->insert()","index":"\u00a0\u00a04\u00a0\u00a0\u00a0\u00a0"},{"file":"APPPATH\\Controllers\\Admin_controllers\\Admin.php:561","function":"\u00a0\u00a0\u00a0\u00a0\u00a0\u00a0\u00a0\u00a0CodeIgniter\\Model->insert()","index":"\u00a0\u00a05\u00a0\u00a0\u00a0\u00a0"},{"file":"SYSTEMPATH\\CodeIgniter.php:933","function":"\u00a0\u00a0\u00a0\u00a0\u00a0\u00a0\u00a0\u00a0App\\Controllers\\Admin_controllers\\Admin->actualizar_juego()","index":"\u00a0\u00a06\u00a0\u00a0\u00a0\u00a0"},{"file":"SYSTEMPATH\\CodeIgniter.php:507","function":"\u00a0\u00a0\u00a0\u00a0\u00a0\u00a0\u00a0\u00a0CodeIgniter\\CodeIgniter->runController()","index":"\u00a0\u00a07\u00a0\u00a0\u00a0\u00a0"},{"file":"SYSTEMPATH\\CodeIgniter.php:354","function":"\u00a0\u00a0\u00a0\u00a0\u00a0\u00a0\u00a0\u00a0CodeIgniter\\CodeIgniter->handleRequest()","index":"\u00a0\u00a08\u00a0\u00a0\u00a0\u00a0"},{"file":"SYSTEMPATH\\Boot.php:334","function":"\u00a0\u00a0\u00a0\u00a0\u00a0\u00a0\u00a0\u00a0CodeIgniter\\CodeIgniter->run()","index":"\u00a0\u00a09\u00a0\u00a0\u00a0\u00a0"},{"file":"SYSTEMPATH\\Boot.php:67","function":"\u00a0\u00a0\u00a0\u00a0\u00a0\u00a0\u00a0\u00a0CodeIgniter\\Boot::runCodeIgniter()","index":"\u00a010\u00a0\u00a0\u00a0\u00a0"},{"file":"FCPATH\\index.php:59","function":"\u00a0\u00a0\u00a0\u00a0\u00a0\u00a0\u00a0\u00a0CodeIgniter\\Boot::bootWeb()","index":"\u00a011\u00a0\u00a0\u00a0\u00a0"}],"trace-file":"APPPATH\\Controllers\\Admin_controllers\\Admin.php:561","qid":"825ae5b9097a78426f7b82c5f95ac7af"},{"hover":"","class":"","duration":"2.23 ms","sql":"<strong>INSERT<\/strong> <strong>INTO<\/strong> `juegos_galeria` (`game_id`, `image_url`) <strong>VALUES<\/strong> (&#039;6&#039;, &#039;https:\/\/shared.fastly.steamstatic.com\/store_item_assets\/steam\/apps\/1091500\/ss_4eb068b1cf52c91b57157b84bed18a186ed7714b.1920x1080.jpg?t=1746519355&#039;)","trace":[{"file":"SYSTEMPATH\\Database\\BaseBuilder.php:2345","function":"\u00a0\u00a0\u00a0\u00a0\u00a0\u00a0\u00a0\u00a0CodeIgniter\\Database\\BaseConnection->query()","index":"\u00a0\u00a01\u00a0\u00a0\u00a0\u00a0"},{"file":"SYSTEMPATH\\Model.php:394","function":"\u00a0\u00a0\u00a0\u00a0\u00a0\u00a0\u00a0\u00a0CodeIgniter\\Database\\BaseBuilder->insert()","index":"\u00a0\u00a02\u00a0\u00a0\u00a0\u00a0"},{"file":"SYSTEMPATH\\BaseModel.php:839","function":"\u00a0\u00a0\u00a0\u00a0\u00a0\u00a0\u00a0\u00a0CodeIgniter\\Model->doInsert()","index":"\u00a0\u00a03\u00a0\u00a0\u00a0\u00a0"},{"file":"SYSTEMPATH\\Model.php:800","function":"\u00a0\u00a0\u00a0\u00a0\u00a0\u00a0\u00a0\u00a0CodeIgniter\\BaseModel->insert()","index":"\u00a0\u00a04\u00a0\u00a0\u00a0\u00a0"},{"file":"APPPATH\\Controllers\\Admin_controllers\\Admin.php:561","function":"\u00a0\u00a0\u00a0\u00a0\u00a0\u00a0\u00a0\u00a0CodeIgniter\\Model->insert()","index":"\u00a0\u00a05\u00a0\u00a0\u00a0\u00a0"},{"file":"SYSTEMPATH\\CodeIgniter.php:933","function":"\u00a0\u00a0\u00a0\u00a0\u00a0\u00a0\u00a0\u00a0App\\Controllers\\Admin_controllers\\Admin->actualizar_juego()","index":"\u00a0\u00a06\u00a0\u00a0\u00a0\u00a0"},{"file":"SYSTEMPATH\\CodeIgniter.php:507","function":"\u00a0\u00a0\u00a0\u00a0\u00a0\u00a0\u00a0\u00a0CodeIgniter\\CodeIgniter->runController()","index":"\u00a0\u00a07\u00a0\u00a0\u00a0\u00a0"},{"file":"SYSTEMPATH\\CodeIgniter.php:354","function":"\u00a0\u00a0\u00a0\u00a0\u00a0\u00a0\u00a0\u00a0CodeIgniter\\CodeIgniter->handleRequest()","index":"\u00a0\u00a08\u00a0\u00a0\u00a0\u00a0"},{"file":"SYSTEMPATH\\Boot.php:334","function":"\u00a0\u00a0\u00a0\u00a0\u00a0\u00a0\u00a0\u00a0CodeIgniter\\CodeIgniter->run()","index":"\u00a0\u00a09\u00a0\u00a0\u00a0\u00a0"},{"file":"SYSTEMPATH\\Boot.php:67","function":"\u00a0\u00a0\u00a0\u00a0\u00a0\u00a0\u00a0\u00a0CodeIgniter\\Boot::runCodeIgniter()","index":"\u00a010\u00a0\u00a0\u00a0\u00a0"},{"file":"FCPATH\\index.php:59","function":"\u00a0\u00a0\u00a0\u00a0\u00a0\u00a0\u00a0\u00a0CodeIgniter\\Boot::bootWeb()","index":"\u00a011\u00a0\u00a0\u00a0\u00a0"}],"trace-file":"APPPATH\\Controllers\\Admin_controllers\\Admin.php:561","qid":"a77e011b181d8e7fd96b2df47febb86c"},{"hover":"","class":"","duration":"2.19 ms","sql":"<strong>INSERT<\/strong> <strong>INTO<\/strong> `juegos_galeria` (`game_id`, `image_url`) <strong>VALUES<\/strong> (&#039;6&#039;, &#039;https:\/\/shared.fastly.steamstatic.com\/store_item_assets\/steam\/apps\/1091500\/ss_8640d9db74f7cad714f6ecfb0e1aceaa3f887e58.1920x1080.jpg?t=1746519355&#039;)","trace":[{"file":"SYSTEMPATH\\Database\\BaseBuilder.php:2345","function":"\u00a0\u00a0\u00a0\u00a0\u00a0\u00a0\u00a0\u00a0CodeIgniter\\Database\\BaseConnection->query()","index":"\u00a0\u00a01\u00a0\u00a0\u00a0\u00a0"},{"file":"SYSTEMPATH\\Model.php:394","function":"\u00a0\u00a0\u00a0\u00a0\u00a0\u00a0\u00a0\u00a0CodeIgniter\\Database\\BaseBuilder->insert()","index":"\u00a0\u00a02\u00a0\u00a0\u00a0\u00a0"},{"file":"SYSTEMPATH\\BaseModel.php:839","function":"\u00a0\u00a0\u00a0\u00a0\u00a0\u00a0\u00a0\u00a0CodeIgniter\\Model->doInsert()","index":"\u00a0\u00a03\u00a0\u00a0\u00a0\u00a0"},{"file":"SYSTEMPATH\\Model.php:800","function":"\u00a0\u00a0\u00a0\u00a0\u00a0\u00a0\u00a0\u00a0CodeIgniter\\BaseModel->insert()","index":"\u00a0\u00a04\u00a0\u00a0\u00a0\u00a0"},{"file":"APPPATH\\Controllers\\Admin_controllers\\Admin.php:561","function":"\u00a0\u00a0\u00a0\u00a0\u00a0\u00a0\u00a0\u00a0CodeIgniter\\Model->insert()","index":"\u00a0\u00a05\u00a0\u00a0\u00a0\u00a0"},{"file":"SYSTEMPATH\\CodeIgniter.php:933","function":"\u00a0\u00a0\u00a0\u00a0\u00a0\u00a0\u00a0\u00a0App\\Controllers\\Admin_controllers\\Admin->actualizar_juego()","index":"\u00a0\u00a06\u00a0\u00a0\u00a0\u00a0"},{"file":"SYSTEMPATH\\CodeIgniter.php:507","function":"\u00a0\u00a0\u00a0\u00a0\u00a0\u00a0\u00a0\u00a0CodeIgniter\\CodeIgniter->runController()","index":"\u00a0\u00a07\u00a0\u00a0\u00a0\u00a0"},{"file":"SYSTEMPATH\\CodeIgniter.php:354","function":"\u00a0\u00a0\u00a0\u00a0\u00a0\u00a0\u00a0\u00a0CodeIgniter\\CodeIgniter->handleRequest()","index":"\u00a0\u00a08\u00a0\u00a0\u00a0\u00a0"},{"file":"SYSTEMPATH\\Boot.php:334","function":"\u00a0\u00a0\u00a0\u00a0\u00a0\u00a0\u00a0\u00a0CodeIgniter\\CodeIgniter->run()","index":"\u00a0\u00a09\u00a0\u00a0\u00a0\u00a0"},{"file":"SYSTEMPATH\\Boot.php:67","function":"\u00a0\u00a0\u00a0\u00a0\u00a0\u00a0\u00a0\u00a0CodeIgniter\\Boot::runCodeIgniter()","index":"\u00a010\u00a0\u00a0\u00a0\u00a0"},{"file":"FCPATH\\index.php:59","function":"\u00a0\u00a0\u00a0\u00a0\u00a0\u00a0\u00a0\u00a0CodeIgniter\\Boot::bootWeb()","index":"\u00a011\u00a0\u00a0\u00a0\u00a0"}],"trace-file":"APPPATH\\Controllers\\Admin_controllers\\Admin.php:561","qid":"ace0352f8f92ec2ab392e788c5aad7d3"},{"hover":"","class":"","duration":"2.29 ms","sql":"DELETE <strong>FROM<\/strong> `juego_requisitos`\n<strong>WHERE<\/strong> `game_id` = &#039;6&#039;","trace":[{"file":"SYSTEMPATH\\Database\\BaseBuilder.php:2848","function":"\u00a0\u00a0\u00a0\u00a0\u00a0\u00a0\u00a0\u00a0CodeIgniter\\Database\\BaseConnection->query()","index":"\u00a0\u00a01\u00a0\u00a0\u00a0\u00a0"},{"file":"SYSTEMPATH\\Model.php:521","function":"\u00a0\u00a0\u00a0\u00a0\u00a0\u00a0\u00a0\u00a0CodeIgniter\\Database\\BaseBuilder->delete()","index":"\u00a0\u00a02\u00a0\u00a0\u00a0\u00a0"},{"file":"SYSTEMPATH\\BaseModel.php:1157","function":"\u00a0\u00a0\u00a0\u00a0\u00a0\u00a0\u00a0\u00a0CodeIgniter\\Model->doDelete()","index":"\u00a0\u00a03\u00a0\u00a0\u00a0\u00a0"},{"file":"APPPATH\\Controllers\\Admin_controllers\\Admin.php:569","function":"\u00a0\u00a0\u00a0\u00a0\u00a0\u00a0\u00a0\u00a0CodeIgniter\\BaseModel->delete()","index":"\u00a0\u00a04\u00a0\u00a0\u00a0\u00a0"},{"file":"SYSTEMPATH\\CodeIgniter.php:933","function":"\u00a0\u00a0\u00a0\u00a0\u00a0\u00a0\u00a0\u00a0App\\Controllers\\Admin_controllers\\Admin->actualizar_juego()","index":"\u00a0\u00a05\u00a0\u00a0\u00a0\u00a0"},{"file":"SYSTEMPATH\\CodeIgniter.php:507","function":"\u00a0\u00a0\u00a0\u00a0\u00a0\u00a0\u00a0\u00a0CodeIgniter\\CodeIgniter->runController()","index":"\u00a0\u00a06\u00a0\u00a0\u00a0\u00a0"},{"file":"SYSTEMPATH\\CodeIgniter.php:354","function":"\u00a0\u00a0\u00a0\u00a0\u00a0\u00a0\u00a0\u00a0CodeIgniter\\CodeIgniter->handleRequest()","index":"\u00a0\u00a07\u00a0\u00a0\u00a0\u00a0"},{"file":"SYSTEMPATH\\Boot.php:334","function":"\u00a0\u00a0\u00a0\u00a0\u00a0\u00a0\u00a0\u00a0CodeIgniter\\CodeIgniter->run()","index":"\u00a0\u00a08\u00a0\u00a0\u00a0\u00a0"},{"file":"SYSTEMPATH\\Boot.php:67","function":"\u00a0\u00a0\u00a0\u00a0\u00a0\u00a0\u00a0\u00a0CodeIgniter\\Boot::runCodeIgniter()","index":"\u00a0\u00a09\u00a0\u00a0\u00a0\u00a0"},{"file":"FCPATH\\index.php:59","function":"\u00a0\u00a0\u00a0\u00a0\u00a0\u00a0\u00a0\u00a0CodeIgniter\\Boot::bootWeb()","index":"\u00a010\u00a0\u00a0\u00a0\u00a0"}],"trace-file":"APPPATH\\Controllers\\Admin_controllers\\Admin.php:569","qid":"ad5fd8b9e1d559de937ff21f360d9056"},{"hover":"","class":"","duration":"2.56 ms","sql":"<strong>INSERT<\/strong> <strong>INTO<\/strong> `juego_requisitos` (`game_id`, `cpu`, `ram`, `gpu`, `storage`, `tipo`) <strong>VALUES<\/strong> (&#039;6&#039;, &#039;Intel Core i5-3570K \/ AMD FX-8310&#039;, &#039;8 GB&#039;, &#039;GTX 780 \/ RX 470&#039;, &#039;70 GB HDD&#039;, &#039;minimo&#039;)","trace":[{"file":"SYSTEMPATH\\Database\\BaseBuilder.php:2345","function":"\u00a0\u00a0\u00a0\u00a0\u00a0\u00a0\u00a0\u00a0CodeIgniter\\Database\\BaseConnection->query()","index":"\u00a0\u00a01\u00a0\u00a0\u00a0\u00a0"},{"file":"SYSTEMPATH\\Model.php:394","function":"\u00a0\u00a0\u00a0\u00a0\u00a0\u00a0\u00a0\u00a0CodeIgniter\\Database\\BaseBuilder->insert()","index":"\u00a0\u00a02\u00a0\u00a0\u00a0\u00a0"},{"file":"SYSTEMPATH\\BaseModel.php:839","function":"\u00a0\u00a0\u00a0\u00a0\u00a0\u00a0\u00a0\u00a0CodeIgniter\\Model->doInsert()","index":"\u00a0\u00a03\u00a0\u00a0\u00a0\u00a0"},{"file":"SYSTEMPATH\\Model.php:800","function":"\u00a0\u00a0\u00a0\u00a0\u00a0\u00a0\u00a0\u00a0CodeIgniter\\BaseModel->insert()","index":"\u00a0\u00a04\u00a0\u00a0\u00a0\u00a0"},{"file":"APPPATH\\Controllers\\Admin_controllers\\Admin.php:571","function":"\u00a0\u00a0\u00a0\u00a0\u00a0\u00a0\u00a0\u00a0CodeIgniter\\Model->insert()","index":"\u00a0\u00a05\u00a0\u00a0\u00a0\u00a0"},{"file":"SYSTEMPATH\\CodeIgniter.php:933","function":"\u00a0\u00a0\u00a0\u00a0\u00a0\u00a0\u00a0\u00a0App\\Controllers\\Admin_controllers\\Admin->actualizar_juego()","index":"\u00a0\u00a06\u00a0\u00a0\u00a0\u00a0"},{"file":"SYSTEMPATH\\CodeIgniter.php:507","function":"\u00a0\u00a0\u00a0\u00a0\u00a0\u00a0\u00a0\u00a0CodeIgniter\\CodeIgniter->runController()","index":"\u00a0\u00a07\u00a0\u00a0\u00a0\u00a0"},{"file":"SYSTEMPATH\\CodeIgniter.php:354","function":"\u00a0\u00a0\u00a0\u00a0\u00a0\u00a0\u00a0\u00a0CodeIgniter\\CodeIgniter->handleRequest()","index":"\u00a0\u00a08\u00a0\u00a0\u00a0\u00a0"},{"file":"SYSTEMPATH\\Boot.php:334","function":"\u00a0\u00a0\u00a0\u00a0\u00a0\u00a0\u00a0\u00a0CodeIgniter\\CodeIgniter->run()","index":"\u00a0\u00a09\u00a0\u00a0\u00a0\u00a0"},{"file":"SYSTEMPATH\\Boot.php:67","function":"\u00a0\u00a0\u00a0\u00a0\u00a0\u00a0\u00a0\u00a0CodeIgniter\\Boot::runCodeIgniter()","index":"\u00a010\u00a0\u00a0\u00a0\u00a0"},{"file":"FCPATH\\index.php:59","function":"\u00a0\u00a0\u00a0\u00a0\u00a0\u00a0\u00a0\u00a0CodeIgniter\\Boot::bootWeb()","index":"\u00a011\u00a0\u00a0\u00a0\u00a0"}],"trace-file":"APPPATH\\Controllers\\Admin_controllers\\Admin.php:571","qid":"7f510849e9538e72f76e13b6768af1aa"},{"hover":"","class":"","duration":"2.19 ms","sql":"<strong>INSERT<\/strong> <strong>INTO<\/strong> `juego_requisitos` (`game_id`, `cpu`, `ram`, `gpu`, `storage`, `tipo`) <strong>VALUES<\/strong> (&#039;6&#039;, &#039;Intel Core i7-12700 \/ AMD Ryzen 7 7800X3D&#039;, &#039;16 GB&#039;, &#039;RTX 3060 \/ RX 6700 XT&#039;, &#039;70 GB SSD&#039;, &#039;recomendado&#039;)","trace":[{"file":"SYSTEMPATH\\Database\\BaseBuilder.php:2345","function":"\u00a0\u00a0\u00a0\u00a0\u00a0\u00a0\u00a0\u00a0CodeIgniter\\Database\\BaseConnection->query()","index":"\u00a0\u00a01\u00a0\u00a0\u00a0\u00a0"},{"file":"SYSTEMPATH\\Model.php:394","function":"\u00a0\u00a0\u00a0\u00a0\u00a0\u00a0\u00a0\u00a0CodeIgniter\\Database\\BaseBuilder->insert()","index":"\u00a0\u00a02\u00a0\u00a0\u00a0\u00a0"},{"file":"SYSTEMPATH\\BaseModel.php:839","function":"\u00a0\u00a0\u00a0\u00a0\u00a0\u00a0\u00a0\u00a0CodeIgniter\\Model->doInsert()","index":"\u00a0\u00a03\u00a0\u00a0\u00a0\u00a0"},{"file":"SYSTEMPATH\\Model.php:800","function":"\u00a0\u00a0\u00a0\u00a0\u00a0\u00a0\u00a0\u00a0CodeIgniter\\BaseModel->insert()","index":"\u00a0\u00a04\u00a0\u00a0\u00a0\u00a0"},{"file":"APPPATH\\Controllers\\Admin_controllers\\Admin.php:579","function":"\u00a0\u00a0\u00a0\u00a0\u00a0\u00a0\u00a0\u00a0CodeIgniter\\Model->insert()","index":"\u00a0\u00a05\u00a0\u00a0\u00a0\u00a0"},{"file":"SYSTEMPATH\\CodeIgniter.php:933","function":"\u00a0\u00a0\u00a0\u00a0\u00a0\u00a0\u00a0\u00a0App\\Controllers\\Admin_controllers\\Admin->actualizar_juego()","index":"\u00a0\u00a06\u00a0\u00a0\u00a0\u00a0"},{"file":"SYSTEMPATH\\CodeIgniter.php:507","function":"\u00a0\u00a0\u00a0\u00a0\u00a0\u00a0\u00a0\u00a0CodeIgniter\\CodeIgniter->runController()","index":"\u00a0\u00a07\u00a0\u00a0\u00a0\u00a0"},{"file":"SYSTEMPATH\\CodeIgniter.php:354","function":"\u00a0\u00a0\u00a0\u00a0\u00a0\u00a0\u00a0\u00a0CodeIgniter\\CodeIgniter->handleRequest()","index":"\u00a0\u00a08\u00a0\u00a0\u00a0\u00a0"},{"file":"SYSTEMPATH\\Boot.php:334","function":"\u00a0\u00a0\u00a0\u00a0\u00a0\u00a0\u00a0\u00a0CodeIgniter\\CodeIgniter->run()","index":"\u00a0\u00a09\u00a0\u00a0\u00a0\u00a0"},{"file":"SYSTEMPATH\\Boot.php:67","function":"\u00a0\u00a0\u00a0\u00a0\u00a0\u00a0\u00a0\u00a0CodeIgniter\\Boot::runCodeIgniter()","index":"\u00a010\u00a0\u00a0\u00a0\u00a0"},{"file":"FCPATH\\index.php:59","function":"\u00a0\u00a0\u00a0\u00a0\u00a0\u00a0\u00a0\u00a0CodeIgniter\\Boot::bootWeb()","index":"\u00a011\u00a0\u00a0\u00a0\u00a0"}],"trace-file":"APPPATH\\Controllers\\Admin_controllers\\Admin.php:579","qid":"a32229db31343b254fd56029651b3c61"},{"hover":"","class":"","duration":"2.22 ms","sql":"<strong>INSERT<\/strong> <strong>INTO<\/strong> `juego_requisitos` (`game_id`, `cpu`, `ram`, `gpu`, `storage`, `tipo`) <strong>VALUES<\/strong> (&#039;6&#039;, &#039;Intel Core i9-13900K \/ AMD Ryzen 9 7950X3D&#039;, &#039;32 GB&#039;, &#039;RTX 4090 \/ RX 7900 XTX&#039;, &#039;70 GB SSD&#039;, &#039;ultra&#039;)","trace":[{"file":"SYSTEMPATH\\Database\\BaseBuilder.php:2345","function":"\u00a0\u00a0\u00a0\u00a0\u00a0\u00a0\u00a0\u00a0CodeIgniter\\Database\\BaseConnection->query()","index":"\u00a0\u00a01\u00a0\u00a0\u00a0\u00a0"},{"file":"SYSTEMPATH\\Model.php:394","function":"\u00a0\u00a0\u00a0\u00a0\u00a0\u00a0\u00a0\u00a0CodeIgniter\\Database\\BaseBuilder->insert()","index":"\u00a0\u00a02\u00a0\u00a0\u00a0\u00a0"},{"file":"SYSTEMPATH\\BaseModel.php:839","function":"\u00a0\u00a0\u00a0\u00a0\u00a0\u00a0\u00a0\u00a0CodeIgniter\\Model->doInsert()","index":"\u00a0\u00a03\u00a0\u00a0\u00a0\u00a0"},{"file":"SYSTEMPATH\\Model.php:800","function":"\u00a0\u00a0\u00a0\u00a0\u00a0\u00a0\u00a0\u00a0CodeIgniter\\BaseModel->insert()","index":"\u00a0\u00a04\u00a0\u00a0\u00a0\u00a0"},{"file":"APPPATH\\Controllers\\Admin_controllers\\Admin.php:587","function":"\u00a0\u00a0\u00a0\u00a0\u00a0\u00a0\u00a0\u00a0CodeIgniter\\Model->insert()","index":"\u00a0\u00a05\u00a0\u00a0\u00a0\u00a0"},{"file":"SYSTEMPATH\\CodeIgniter.php:933","function":"\u00a0\u00a0\u00a0\u00a0\u00a0\u00a0\u00a0\u00a0App\\Controllers\\Admin_controllers\\Admin->actualizar_juego()","index":"\u00a0\u00a06\u00a0\u00a0\u00a0\u00a0"},{"file":"SYSTEMPATH\\CodeIgniter.php:507","function":"\u00a0\u00a0\u00a0\u00a0\u00a0\u00a0\u00a0\u00a0CodeIgniter\\CodeIgniter->runController()","index":"\u00a0\u00a07\u00a0\u00a0\u00a0\u00a0"},{"file":"SYSTEMPATH\\CodeIgniter.php:354","function":"\u00a0\u00a0\u00a0\u00a0\u00a0\u00a0\u00a0\u00a0CodeIgniter\\CodeIgniter->handleRequest()","index":"\u00a0\u00a08\u00a0\u00a0\u00a0\u00a0"},{"file":"SYSTEMPATH\\Boot.php:334","function":"\u00a0\u00a0\u00a0\u00a0\u00a0\u00a0\u00a0\u00a0CodeIgniter\\CodeIgniter->run()","index":"\u00a0\u00a09\u00a0\u00a0\u00a0\u00a0"},{"file":"SYSTEMPATH\\Boot.php:67","function":"\u00a0\u00a0\u00a0\u00a0\u00a0\u00a0\u00a0\u00a0CodeIgniter\\Boot::runCodeIgniter()","index":"\u00a010\u00a0\u00a0\u00a0\u00a0"},{"file":"FCPATH\\index.php:59","function":"\u00a0\u00a0\u00a0\u00a0\u00a0\u00a0\u00a0\u00a0CodeIgniter\\Boot::bootWeb()","index":"\u00a011\u00a0\u00a0\u00a0\u00a0"}],"trace-file":"APPPATH\\Controllers\\Admin_controllers\\Admin.php:587","qid":"0a84a5d52d2c199421d327f16456677f"}]},"badgeValue":17,"isEmpty":false,"hasTabContent":true,"hasLabel":false,"icon":"data:image\/png;base64,iVBORw0KGgoAAAANSUhEUgAAABgAAAAYCAYAAADgdz34AAAAAXNSR0IArs4c6QAAAARnQU1BAACxjwv8YQUAAAAJcEhZcwAADsMAAA7DAcdvqGQAAADMSURBVEhLY6A3YExLSwsA4nIycQDIDIhRWEBqamo\/UNF\/SjDQjF6ocZgAKPkRiFeEhoYyQ4WIBiA9QAuWAPEHqBAmgLqgHcolGQD1V4DMgHIxwbCxYD+QBqcKINseKo6eWrBioPrtQBq\/BcgY5ht0cUIYbBg2AJKkRxCNWkDQgtFUNJwtABr+F6igE8olGQD114HMgHIxAVDyAhA\/AlpSA8RYUwoeXAPVex5qHCbIyMgwBCkAuQJIY00huDBUz\/mUlBQDqHGjgBjAwAAACexpph6oHSQAAAAASUVORK5CYII=","hasTimelineData":true,"timelineData":[{"name":"Connecting to Database: \"default\"","component":"Database","start":1749941889.968872,"duration":"0.000995"},{"name":"Query","component":"Database","start":1749941889.970658,"duration":"0.002597","query":"<strong>UPDATE<\/strong> `juegos` SET `title` = &#039;Cyberpunk 2077&#039;, `price` = &#039;29.99&#039;, `release_date` = &#039;2020-12-10&#039;, `developer` = &#039;CD Projekt RED&#039;, `rating` = &#039;8.0&#039;, `about` = &#039;Un RPG de mundo abierto ambientado en un futuro dist\u00f3pico lleno de acci\u00f3n, tecnolog\u00eda y decisiones.&#039;, `synopsis` = &#039;Cyberpunk 2077 transporta a los jugadores a Night City, una metr\u00f3polis obsesionada con el poder, la modificaci\u00f3n corporal y el estatus. Interpret\u00e1s a V, un mercenario en busca de un implante que puede otorgar la inmortalidad.\\r\\n\\r\\nA pesar de un lanzamiento pol\u00e9mico, el juego se ha pulido con el tiempo y ofrece una experiencia profunda, con una narrativa no lineal, m\u00faltiples finales y una ambientaci\u00f3n vibrante que da vida a un mundo cyberpunk como nunca antes.&#039;, `youtube_trailer_id` = &#039;8X2kIfS6fb8?si=pwOQQLVDsxTOdGv4&#039;, `cover_image_url` = &#039;https:\/\/cdn2.steamgriddb.com\/grid\/f39b781760a403dedaa05587e8889c1a.png&#039;, `card_image_url` = &#039;https:\/\/cdn2.steamgriddb.com\/grid\/796c4dde50f3fcea641e99ab0fb6dc70.jpg&#039;, `banner_image_url` = &#039;https:\/\/cdn2.steamgriddb.com\/hero\/fb87582825f9d28a8d42c5e5e5e8b23d.png&#039;, `logo_url` = &#039;https:\/\/cdn2.steamgriddb.com\/logo\/2b2e7393b05b5b52af65bf2ed7f4ad4f.png&#039;, `updated_at` = &#039;2025-06-14 22:58:09&#039;\n<strong>WHERE<\/strong> `juegos`.`game_id` <strong>IN<\/strong> (&#039;6&#039;)"},{"name":"Query","component":"Database","start":1749941889.973354,"duration":"0.002221","query":"DELETE <strong>FROM<\/strong> `juego_categorias`\n<strong>WHERE<\/strong> `game_id` = &#039;6&#039;"},{"name":"Query","component":"Database","start":1749941889.975657,"duration":"0.002207","query":"<strong>INSERT<\/strong> <strong>INTO<\/strong> `juego_categorias` (`game_id`, `category_id`) <strong>VALUES<\/strong> (&#039;6&#039;, &#039;1&#039;)"},{"name":"Query","component":"Database","start":1749941889.977924,"duration":"0.002406","query":"<strong>INSERT<\/strong> <strong>INTO<\/strong> `juego_categorias` (`game_id`, `category_id`) <strong>VALUES<\/strong> (&#039;6&#039;, &#039;2&#039;)"},{"name":"Query","component":"Database","start":1749941889.980388,"duration":"0.002197","query":"<strong>INSERT<\/strong> <strong>INTO<\/strong> `juego_categorias` (`game_id`, `category_id`) <strong>VALUES<\/strong> (&#039;6&#039;, &#039;7&#039;)"},{"name":"Query","component":"Database","start":1749941889.982639,"duration":"0.002181","query":"<strong>INSERT<\/strong> <strong>INTO<\/strong> `juego_categorias` (`game_id`, `category_id`) <strong>VALUES<\/strong> (&#039;6&#039;, &#039;9&#039;)"},{"name":"Query","component":"Database","start":1749941889.984889,"duration":"0.002182","query":"<strong>INSERT<\/strong> <strong>INTO<\/strong> `juego_categorias` (`game_id`, `category_id`) <strong>VALUES<\/strong> (&#039;6&#039;, &#039;10&#039;)"},{"name":"Query","component":"Database","start":1749941889.987137,"duration":"0.002350","query":"<strong>INSERT<\/strong> <strong>INTO<\/strong> `juego_categorias` (`game_id`, `category_id`) <strong>VALUES<\/strong> (&#039;6&#039;, &#039;11&#039;)"},{"name":"Query","component":"Database","start":1749941889.989564,"duration":"0.002207","query":"DELETE <strong>FROM<\/strong> `juegos_galeria`\n<strong>WHERE<\/strong> `game_id` = &#039;6&#039;"},{"name":"Query","component":"Database","start":1749941889.991841,"duration":"0.002660","query":"<strong>INSERT<\/strong> <strong>INTO<\/strong> `juegos_galeria` (`game_id`, `image_url`) <strong>VALUES<\/strong> (&#039;6&#039;, &#039;https:\/\/shared.fastly.steamstatic.com\/store_item_assets\/steam\/apps\/1091500\/ss_7924f64b6e5d586a80418c9896a1c92881a7905b.1920x1080.jpg?t=1746519355&#039;)"},{"name":"Query","component":"Database","start":1749941889.994567,"duration":"0.002414","query":"<strong>INSERT<\/strong> <strong>INTO<\/strong> `juegos_galeria` (`game_id`, `image_url`) <strong>VALUES<\/strong> (&#039;6&#039;, &#039;https:\/\/shared.fastly.steamstatic.com\/store_item_assets\/steam\/apps\/1091500\/ss_b529b0abc43f55fc23fe8058eddb6e37c9629a6a.1920x1080.jpg?t=1746519355&#039;)"},{"name":"Query","component":"Database","start":1749941889.997065,"duration":"0.002233","query":"<strong>INSERT<\/strong> <strong>INTO<\/strong> `juegos_galeria` (`game_id`, `image_url`) <strong>VALUES<\/strong> (&#039;6&#039;, &#039;https:\/\/shared.fastly.steamstatic.com\/store_item_assets\/steam\/apps\/1091500\/ss_4eb068b1cf52c91b57157b84bed18a186ed7714b.1920x1080.jpg?t=1746519355&#039;)"},{"name":"Query","component":"Database","start":1749941889.999348,"duration":"0.002187","query":"<strong>INSERT<\/strong> <strong>INTO<\/strong> `juegos_galeria` (`game_id`, `image_url`) <strong>VALUES<\/strong> (&#039;6&#039;, &#039;https:\/\/shared.fastly.steamstatic.com\/store_item_assets\/steam\/apps\/1091500\/ss_8640d9db74f7cad714f6ecfb0e1aceaa3f887e58.1920x1080.jpg?t=1746519355&#039;)"},{"name":"Query","component":"Database","start":1749941890.001615,"duration":"0.002285","query":"DELETE <strong>FROM<\/strong> `juego_requisitos`\n<strong>WHERE<\/strong> `game_id` = &#039;6&#039;"},{"name":"Query","component":"Database","start":1749941890.003992,"duration":"0.002558","query":"<strong>INSERT<\/strong> <strong>INTO<\/strong> `juego_requisitos` (`game_id`, `cpu`, `ram`, `gpu`, `storage`, `tipo`) <strong>VALUES<\/strong> (&#039;6&#039;, &#039;Intel Core i5-3570K \/ AMD FX-8310&#039;, &#039;8 GB&#039;, &#039;GTX 780 \/ RX 470&#039;, &#039;70 GB HDD&#039;, &#039;minimo&#039;)"},{"name":"Query","component":"Database","start":1749941890.006637,"duration":"0.002186","query":"<strong>INSERT<\/strong> <strong>INTO<\/strong> `juego_requisitos` (`game_id`, `cpu`, `ram`, `gpu`, `storage`, `tipo`) <strong>VALUES<\/strong> (&#039;6&#039;, &#039;Intel Core i7-12700 \/ AMD Ryzen 7 7800X3D&#039;, &#039;16 GB&#039;, &#039;RTX 3060 \/ RX 6700 XT&#039;, &#039;70 GB SSD&#039;, &#039;recomendado&#039;)"},{"name":"Query","component":"Database","start":1749941890.008895,"duration":"0.002216","query":"<strong>INSERT<\/strong> <strong>INTO<\/strong> `juego_requisitos` (`game_id`, `cpu`, `ram`, `gpu`, `storage`, `tipo`) <strong>VALUES<\/strong> (&#039;6&#039;, &#039;Intel Core i9-13900K \/ AMD Ryzen 9 7950X3D&#039;, &#039;32 GB&#039;, &#039;RTX 4090 \/ RX 7900 XTX&#039;, &#039;70 GB SSD&#039;, &#039;ultra&#039;)"}]},{"title":"Logs","titleSafe":"logs","titleDetails":"","display":{"logs":[{"level":"debug","msg":"Session: Class initialized using 'CodeIgniter\\Session\\Handlers\\FileHandler' driver."}]},"badgeValue":null,"isEmpty":false,"hasTabContent":true,"hasLabel":false,"icon":"data:image\/png;base64,iVBORw0KGgoAAAANSUhEUgAAABgAAAAYCAYAAADgdz34AAAAAXNSR0IArs4c6QAAAARnQU1BAACxjwv8YQUAAAAJcEhZcwAADsMAAA7DAcdvqGQAAACYSURBVEhLYxgFJIHU1FSjtLS0i0D8AYj7gEKMEBkqAaAFF4D4ERCvAFrwH4gDoFIMKSkpFkB+OTEYqgUTACXfA\/GqjIwMQyD9H2hRHlQKJFcBEiMGQ7VgAqCBvUgK32dmZspCpagGGNPT0\/1BLqeF4bQHQJePpiIwhmrBBEADR1MRfgB0+WgqAmOoFkwANHA0FY0CUgEDAwCQ0PUpNB3kqwAAAABJRU5ErkJggg==","hasTimelineData":false,"timelineData":[]},{"title":"Views","titleSafe":"views","titleDetails":"","display":[],"badgeValue":0,"isEmpty":false,"hasTabContent":false,"hasLabel":true,"icon":"data:image\/png;base64,iVBORw0KGgoAAAANSUhEUgAAABgAAAAYCAYAAADgdz34AAAAAXNSR0IArs4c6QAAAARnQU1BAACxjwv8YQUAAAAJcEhZcwAADsMAAA7DAcdvqGQAAADeSURBVEhL7ZSxDcIwEEWNYA0YgGmgyAaJLTcUaaBzQQEVjMEabBQxAdw53zTHiThEovGTfnE\/9rsoRUxhKLOmaa6Uh7X2+UvguLCzVxN1XW9x4EYHzik033Hp3X0LO+DaQG8MDQcuq6qao4qkHuMgQggLvkPLjqh00ZgFDBacMJYFkuwFlH1mshdkZ5JPJERA9JpI6xNCBESvibQ+IURA9JpI6xNCBESvibQ+IURA9DTsuHTOrVFFxixgB\/eUFlU8uKJ0eDBFOu\/9EvoeKnlJS2\/08Tc8NOwQ8sIfMeYFjqKDjdU2sp4AAAAASUVORK5CYII=","hasTimelineData":true,"timelineData":[]},{"title":"Files","titleSafe":"files","titleDetails":"( 162 )","display":{"coreFiles":[{"path":"SYSTEMPATH\\API\\ResponseTrait.php","name":"ResponseTrait.php"},{"path":"SYSTEMPATH\\Autoloader\\Autoloader.php","name":"Autoloader.php"},{"path":"SYSTEMPATH\\Autoloader\\FileLocator.php","name":"FileLocator.php"},{"path":"SYSTEMPATH\\Autoloader\\FileLocatorInterface.php","name":"FileLocatorInterface.php"},{"path":"SYSTEMPATH\\BaseModel.php","name":"BaseModel.php"},{"path":"SYSTEMPATH\\Boot.php","name":"Boot.php"},{"path":"SYSTEMPATH\\Cache\\CacheFactory.php","name":"CacheFactory.php"},{"path":"SYSTEMPATH\\Cache\\CacheInterface.php","name":"CacheInterface.php"},{"path":"SYSTEMPATH\\Cache\\Handlers\\BaseHandler.php","name":"BaseHandler.php"},{"path":"SYSTEMPATH\\Cache\\Handlers\\FileHandler.php","name":"FileHandler.php"},{"path":"SYSTEMPATH\\Cache\\ResponseCache.php","name":"ResponseCache.php"},{"path":"SYSTEMPATH\\CodeIgniter.php","name":"CodeIgniter.php"},{"path":"SYSTEMPATH\\Common.php","name":"Common.php"},{"path":"SYSTEMPATH\\Config\\AutoloadConfig.php","name":"AutoloadConfig.php"},{"path":"SYSTEMPATH\\Config\\BaseConfig.php","name":"BaseConfig.php"},{"path":"SYSTEMPATH\\Config\\BaseService.php","name":"BaseService.php"},{"path":"SYSTEMPATH\\Config\\DotEnv.php","name":"DotEnv.php"},{"path":"SYSTEMPATH\\Config\\Factories.php","name":"Factories.php"},{"path":"SYSTEMPATH\\Config\\Factory.php","name":"Factory.php"},{"path":"SYSTEMPATH\\Config\\Filters.php","name":"Filters.php"},{"path":"SYSTEMPATH\\Config\\Routing.php","name":"Routing.php"},{"path":"SYSTEMPATH\\Config\\Services.php","name":"Services.php"},{"path":"SYSTEMPATH\\Config\\View.php","name":"View.php"},{"path":"SYSTEMPATH\\Controller.php","name":"Controller.php"},{"path":"SYSTEMPATH\\Cookie\\CloneableCookieInterface.php","name":"CloneableCookieInterface.php"},{"path":"SYSTEMPATH\\Cookie\\Cookie.php","name":"Cookie.php"},{"path":"SYSTEMPATH\\Cookie\\CookieInterface.php","name":"CookieInterface.php"},{"path":"SYSTEMPATH\\Cookie\\CookieStore.php","name":"CookieStore.php"},{"path":"SYSTEMPATH\\Database\\BaseBuilder.php","name":"BaseBuilder.php"},{"path":"SYSTEMPATH\\Database\\BaseConnection.php","name":"BaseConnection.php"},{"path":"SYSTEMPATH\\Database\\Config.php","name":"Config.php"},{"path":"SYSTEMPATH\\Database\\ConnectionInterface.php","name":"ConnectionInterface.php"},{"path":"SYSTEMPATH\\Database\\Database.php","name":"Database.php"},{"path":"SYSTEMPATH\\Database\\MySQLi\\Builder.php","name":"Builder.php"},{"path":"SYSTEMPATH\\Database\\MySQLi\\Connection.php","name":"Connection.php"},{"path":"SYSTEMPATH\\Database\\Query.php","name":"Query.php"},{"path":"SYSTEMPATH\\Database\\QueryInterface.php","name":"QueryInterface.php"},{"path":"SYSTEMPATH\\Debug\\Exceptions.php","name":"Exceptions.php"},{"path":"SYSTEMPATH\\Debug\\Timer.php","name":"Timer.php"},{"path":"SYSTEMPATH\\Debug\\Toolbar.php","name":"Toolbar.php"},{"path":"SYSTEMPATH\\Debug\\Toolbar\\Collectors\\BaseCollector.php","name":"BaseCollector.php"},{"path":"SYSTEMPATH\\Debug\\Toolbar\\Collectors\\Database.php","name":"Database.php"},{"path":"SYSTEMPATH\\Debug\\Toolbar\\Collectors\\Events.php","name":"Events.php"},{"path":"SYSTEMPATH\\Debug\\Toolbar\\Collectors\\Files.php","name":"Files.php"},{"path":"SYSTEMPATH\\Debug\\Toolbar\\Collectors\\Logs.php","name":"Logs.php"},{"path":"SYSTEMPATH\\Debug\\Toolbar\\Collectors\\Routes.php","name":"Routes.php"},{"path":"SYSTEMPATH\\Debug\\Toolbar\\Collectors\\Timers.php","name":"Timers.php"},{"path":"SYSTEMPATH\\Debug\\Toolbar\\Collectors\\Views.php","name":"Views.php"},{"path":"SYSTEMPATH\\Events\\Events.php","name":"Events.php"},{"path":"SYSTEMPATH\\Filters\\DebugToolbar.php","name":"DebugToolbar.php"},{"path":"SYSTEMPATH\\Filters\\FilterInterface.php","name":"FilterInterface.php"},{"path":"SYSTEMPATH\\Filters\\Filters.php","name":"Filters.php"},{"path":"SYSTEMPATH\\Filters\\ForceHTTPS.php","name":"ForceHTTPS.php"},{"path":"SYSTEMPATH\\Filters\\PageCache.php","name":"PageCache.php"},{"path":"SYSTEMPATH\\Filters\\PerformanceMetrics.php","name":"PerformanceMetrics.php"},{"path":"SYSTEMPATH\\HTTP\\ContentSecurityPolicy.php","name":"ContentSecurityPolicy.php"},{"path":"SYSTEMPATH\\HTTP\\Header.php","name":"Header.php"},{"path":"SYSTEMPATH\\HTTP\\IncomingRequest.php","name":"IncomingRequest.php"},{"path":"SYSTEMPATH\\HTTP\\Message.php","name":"Message.php"},{"path":"SYSTEMPATH\\HTTP\\MessageInterface.php","name":"MessageInterface.php"},{"path":"SYSTEMPATH\\HTTP\\MessageTrait.php","name":"MessageTrait.php"},{"path":"SYSTEMPATH\\HTTP\\Method.php","name":"Method.php"},{"path":"SYSTEMPATH\\HTTP\\OutgoingRequest.php","name":"OutgoingRequest.php"},{"path":"SYSTEMPATH\\HTTP\\OutgoingRequestInterface.php","name":"OutgoingRequestInterface.php"},{"path":"SYSTEMPATH\\HTTP\\RedirectResponse.php","name":"RedirectResponse.php"},{"path":"SYSTEMPATH\\HTTP\\Request.php","name":"Request.php"},{"path":"SYSTEMPATH\\HTTP\\RequestInterface.php","name":"RequestInterface.php"},{"path":"SYSTEMPATH\\HTTP\\RequestTrait.php","name":"RequestTrait.php"},{"path":"SYSTEMPATH\\HTTP\\Response.php","name":"Response.php"},{"path":"SYSTEMPATH\\HTTP\\ResponseInterface.php","name":"ResponseInterface.php"},{"path":"SYSTEMPATH\\HTTP\\ResponseTrait.php","name":"ResponseTrait.php"},{"path":"SYSTEMPATH\\HTTP\\SiteURI.php","name":"SiteURI.php"},{"path":"SYSTEMPATH\\HTTP\\SiteURIFactory.php","name":"SiteURIFactory.php"},{"path":"SYSTEMPATH\\HTTP\\URI.php","name":"URI.php"},{"path":"SYSTEMPATH\\HTTP\\UserAgent.php","name":"UserAgent.php"},{"path":"SYSTEMPATH\\Helpers\\Array\\ArrayHelper.php","name":"ArrayHelper.php"},{"path":"SYSTEMPATH\\Helpers\\array_helper.php","name":"array_helper.php"},{"path":"SYSTEMPATH\\Helpers\\kint_helper.php","name":"kint_helper.php"},{"path":"SYSTEMPATH\\Helpers\\url_helper.php","name":"url_helper.php"},{"path":"SYSTEMPATH\\I18n\\Time.php","name":"Time.php"},{"path":"SYSTEMPATH\\I18n\\TimeTrait.php","name":"TimeTrait.php"},{"path":"SYSTEMPATH\\Log\\Handlers\\BaseHandler.php","name":"BaseHandler.php"},{"path":"SYSTEMPATH\\Log\\Handlers\\FileHandler.php","name":"FileHandler.php"},{"path":"SYSTEMPATH\\Log\\Handlers\\HandlerInterface.php","name":"HandlerInterface.php"},{"path":"SYSTEMPATH\\Log\\Logger.php","name":"Logger.php"},{"path":"SYSTEMPATH\\Model.php","name":"Model.php"},{"path":"SYSTEMPATH\\Modules\\Modules.php","name":"Modules.php"},{"path":"SYSTEMPATH\\Router\\RouteCollection.php","name":"RouteCollection.php"},{"path":"SYSTEMPATH\\Router\\RouteCollectionInterface.php","name":"RouteCollectionInterface.php"},{"path":"SYSTEMPATH\\Router\\Router.php","name":"Router.php"},{"path":"SYSTEMPATH\\Router\\RouterInterface.php","name":"RouterInterface.php"},{"path":"SYSTEMPATH\\Session\\Handlers\\BaseHandler.php","name":"BaseHandler.php"},{"path":"SYSTEMPATH\\Session\\Handlers\\FileHandler.php","name":"FileHandler.php"},{"path":"SYSTEMPATH\\Session\\Session.php","name":"Session.php"},{"path":"SYSTEMPATH\\Session\\SessionInterface.php","name":"SessionInterface.php"},{"path":"SYSTEMPATH\\Superglobals.php","name":"Superglobals.php"},{"path":"SYSTEMPATH\\ThirdParty\\Escaper\\Escaper.php","name":"Escaper.php"},{"path":"SYSTEMPATH\\ThirdParty\\Kint\\FacadeInterface.php","name":"FacadeInterface.php"},{"path":"SYSTEMPATH\\ThirdParty\\Kint\\Kint.php","name":"Kint.php"},{"path":"SYSTEMPATH\\ThirdParty\\Kint\\Renderer\\AbstractRenderer.php","name":"AbstractRenderer.php"},{"path":"SYSTEMPATH\\ThirdParty\\Kint\\Renderer\\AssetRendererTrait.php","name":"AssetRendererTrait.php"},{"path":"SYSTEMPATH\\ThirdParty\\Kint\\Renderer\\CliRenderer.php","name":"CliRenderer.php"},{"path":"SYSTEMPATH\\ThirdParty\\Kint\\Renderer\\ConstructableRendererInterface.php","name":"ConstructableRendererInterface.php"},{"path":"SYSTEMPATH\\ThirdParty\\Kint\\Renderer\\RendererInterface.php","name":"RendererInterface.php"},{"path":"SYSTEMPATH\\ThirdParty\\Kint\\Renderer\\RichRenderer.php","name":"RichRenderer.php"},{"path":"SYSTEMPATH\\ThirdParty\\Kint\\Renderer\\TextRenderer.php","name":"TextRenderer.php"},{"path":"SYSTEMPATH\\ThirdParty\\Kint\\Utils.php","name":"Utils.php"},{"path":"SYSTEMPATH\\ThirdParty\\Kint\\init.php","name":"init.php"},{"path":"SYSTEMPATH\\ThirdParty\\Kint\\init_helpers.php","name":"init_helpers.php"},{"path":"SYSTEMPATH\\ThirdParty\\PSR\\Log\\LogLevel.php","name":"LogLevel.php"},{"path":"SYSTEMPATH\\ThirdParty\\PSR\\Log\\LoggerAwareTrait.php","name":"LoggerAwareTrait.php"},{"path":"SYSTEMPATH\\ThirdParty\\PSR\\Log\\LoggerInterface.php","name":"LoggerInterface.php"},{"path":"SYSTEMPATH\\Traits\\ConditionalTrait.php","name":"ConditionalTrait.php"},{"path":"SYSTEMPATH\\Validation\\CreditCardRules.php","name":"CreditCardRules.php"},{"path":"SYSTEMPATH\\Validation\\DotArrayFilter.php","name":"DotArrayFilter.php"},{"path":"SYSTEMPATH\\Validation\\FormatRules.php","name":"FormatRules.php"},{"path":"SYSTEMPATH\\Validation\\Rules.php","name":"Rules.php"},{"path":"SYSTEMPATH\\Validation\\StrictRules\\CreditCardRules.php","name":"CreditCardRules.php"},{"path":"SYSTEMPATH\\Validation\\StrictRules\\FileRules.php","name":"FileRules.php"},{"path":"SYSTEMPATH\\Validation\\StrictRules\\FormatRules.php","name":"FormatRules.php"},{"path":"SYSTEMPATH\\Validation\\StrictRules\\Rules.php","name":"Rules.php"},{"path":"SYSTEMPATH\\Validation\\Validation.php","name":"Validation.php"},{"path":"SYSTEMPATH\\Validation\\ValidationInterface.php","name":"ValidationInterface.php"},{"path":"SYSTEMPATH\\View\\RendererInterface.php","name":"RendererInterface.php"},{"path":"SYSTEMPATH\\View\\View.php","name":"View.php"},{"path":"SYSTEMPATH\\View\\ViewDecoratorTrait.php","name":"ViewDecoratorTrait.php"}],"userFiles":[{"path":"APPPATH\\Common.php","name":"Common.php"},{"path":"APPPATH\\Config\\App.php","name":"App.php"},{"path":"APPPATH\\Config\\Autoload.php","name":"Autoload.php"},{"path":"APPPATH\\Config\\Boot\\development.php","name":"development.php"},{"path":"APPPATH\\Config\\Cache.php","name":"Cache.php"},{"path":"APPPATH\\Config\\Constants.php","name":"Constants.php"},{"path":"APPPATH\\Config\\ContentSecurityPolicy.php","name":"ContentSecurityPolicy.php"},{"path":"APPPATH\\Config\\Cookie.php","name":"Cookie.php"},{"path":"APPPATH\\Config\\Database.php","name":"Database.php"},{"path":"APPPATH\\Config\\Events.php","name":"Events.php"},{"path":"APPPATH\\Config\\Exceptions.php","name":"Exceptions.php"},{"path":"APPPATH\\Config\\Feature.php","name":"Feature.php"},{"path":"APPPATH\\Config\\Filters.php","name":"Filters.php"},{"path":"APPPATH\\Config\\Kint.php","name":"Kint.php"},{"path":"APPPATH\\Config\\Logger.php","name":"Logger.php"},{"path":"APPPATH\\Config\\Modules.php","name":"Modules.php"},{"path":"APPPATH\\Config\\Optimize.php","name":"Optimize.php"},{"path":"APPPATH\\Config\\Paths.php","name":"Paths.php"},{"path":"APPPATH\\Config\\Routes.php","name":"Routes.php"},{"path":"APPPATH\\Config\\Routing.php","name":"Routing.php"},{"path":"APPPATH\\Config\\Services.php","name":"Services.php"},{"path":"APPPATH\\Config\\Session.php","name":"Session.php"},{"path":"APPPATH\\Config\\Toolbar.php","name":"Toolbar.php"},{"path":"APPPATH\\Config\\UserAgents.php","name":"UserAgents.php"},{"path":"APPPATH\\Config\\Validation.php","name":"Validation.php"},{"path":"APPPATH\\Config\\View.php","name":"View.php"},{"path":"APPPATH\\Controllers\\Admin_controllers\\Admin.php","name":"Admin.php"},{"path":"APPPATH\\Controllers\\BaseController.php","name":"BaseController.php"},{"path":"APPPATH\\Models\\CategoriaModel.php","name":"CategoriaModel.php"},{"path":"APPPATH\\Models\\GaleriaModel.php","name":"GaleriaModel.php"},{"path":"APPPATH\\Models\\JuegoCategoriaModel.php","name":"JuegoCategoriaModel.php"},{"path":"APPPATH\\Models\\JuegosModel.php","name":"JuegosModel.php"},{"path":"APPPATH\\Models\\RequisitosModel.php","name":"RequisitosModel.php"},{"path":"APPPATH\\Models\\ReviewModel.php","name":"ReviewModel.php"},{"path":"APPPATH\\Models\\UsuarioModel.php","name":"UsuarioModel.php"},{"path":"FCPATH\\index.php","name":"index.php"}]},"badgeValue":162,"isEmpty":false,"hasTabContent":true,"hasLabel":false,"icon":"data:image\/png;base64,iVBORw0KGgoAAAANSUhEUgAAABgAAAAYCAYAAADgdz34AAAAAXNSR0IArs4c6QAAAARnQU1BAACxjwv8YQUAAAAJcEhZcwAADsMAAA7DAcdvqGQAAAGBSURBVEhL7ZQ9S8NQGIVTBQUncfMfCO4uLgoKbuKQOWg+OkXERRE1IAXrIHbVDrqIDuLiJgj+gro7S3dnpfq88b1FMTE3VZx64HBzzvvZWxKnj15QCcPwCD5HUfSWR+JtzgmtsUcQBEva5IIm9SwSu+95CAWbUuy67qBa32ByZEDpIaZYZSZMjjQuPcQUq8yEyYEb8FSerYeQVGbAFzJkX1PyQWLhgCz0BxTCekC1Wp0hsa6yokzhed4oje6Iz6rlJEkyIKfUEFtITVtQdAibn5rMyaYsMS+a5wTv8qeXMhcU16QZbKgl3hbs+L4\/pnpdc87MElZgq10p5DxGdq8I7xrvUWUKvG3NbSK7ubngYzdJwSsF7TiOh9VOgfcEz1UayNe3JUPM1RWC5GXYgTfc75B4NBmXJnAtTfpABX0iPvEd9ezALwkplCFXcr9styiNOKc1RRZpaPM9tcqBwlWzGY1qPL9wjqRBgF5BH6j8HWh2S7MHlX8PrmbK+k\/8PzjOOzx1D3i1pKTTAAAAAElFTkSuQmCC","hasTimelineData":false,"timelineData":[]},{"title":"Routes","titleSafe":"routes","titleDetails":"","display":{"matchedRoute":[{"directory":"","controller":"\\App\\Controllers\\Admin_controllers\\Admin","method":"actualizar_juego","paramCount":1,"truePCount":1,"params":[{"name":"$id = ","value":"6"}]}],"routes":[{"method":"GET","route":"\/","handler":"\\App\\Controllers\\Home::index"},{"method":"GET","route":"ofertas","handler":"\\App\\Controllers\\Juegos::ofertas"},{"method":"GET","route":"populares","handler":"\\App\\Controllers\\Juegos::populares"},{"method":"GET","route":"juego\/([0-9]+)","handler":"\\App\\Controllers\\Juegos::detalle\/$1"},{"method":"GET","route":"nosotros","handler":"\\App\\Controllers\\Home::nosotros"},{"method":"GET","route":"juegos","handler":"\\App\\Controllers\\Juegos::all_games"},{"method":"GET","route":"comercializacion","handler":"\\App\\Controllers\\Home::comercializacion"},{"method":"GET","route":"contacto","handler":"\\App\\Controllers\\Home::contacto"},{"method":"GET","route":"error_contacto","handler":"\\App\\Controllers\\Home::error_contacto"},{"method":"GET","route":"terminos","handler":"\\App\\Controllers\\Home::terminos"},{"method":"GET","route":"cart","handler":"\\App\\Controllers\\Home::cart"},{"method":"GET","route":"wishlist","handler":"\\App\\Controllers\\Home::wishlist"},{"method":"GET","route":"pago","handler":"\\App\\Controllers\\Home::pago"},{"method":"GET","route":"confirmacion","handler":"\\App\\Controllers\\Home::confirmacion"},{"method":"GET","route":"login","handler":"\\App\\Controllers\\Home::login"},{"method":"GET","route":"register","handler":"\\App\\Controllers\\Home::register"},{"method":"GET","route":"recuperar","handler":"\\App\\Controllers\\Home::recuperar"},{"method":"GET","route":"nueva-pass","handler":"\\App\\Controllers\\Home::new_pass"},{"method":"GET","route":"user-profile","handler":"\\App\\Controllers\\UserProfile::perfil"},{"method":"GET","route":"datos_usuario","handler":"\\App\\Controllers\\UserProfile::datos_usuario"},{"method":"GET","route":"juego\/([0-9]+)\/filtrar-resenas","handler":"\\App\\Controllers\\Juegos::filtrarResenas\/$1"},{"method":"GET","route":"perfil","handler":"\\App\\Controllers\\Admin_controllers\\Admin::admin"},{"method":"GET","route":"perfil\/admin-juegos","handler":"\\App\\Controllers\\Admin_controllers\\Admin::admin_juegos"},{"method":"GET","route":"perfil\/admin-usuarios","handler":"\\App\\Controllers\\Admin_controllers\\Admin::admin_usuarios"},{"method":"GET","route":"perfil\/admin-categorias","handler":"\\App\\Controllers\\Admin_controllers\\Admin::admin_categorias"},{"method":"GET","route":"perfil\/obtener-juego\/([0-9]+)","handler":"\\App\\Controllers\\Admin_controllers\\Admin::obtener_juego\/$1"},{"method":"GET","route":"([^\/]+)","handler":"\\App\\Controllers\\Juegos::categoria\/$1"},{"method":"POST","route":"consulta","handler":"\\App\\Controllers\\Usuario::add_consulta"},{"method":"POST","route":"procesar_login","handler":"\\App\\Controllers\\Usuario::procesar_login"},{"method":"POST","route":"procesar_registro","handler":"\\App\\Controllers\\Usuario::procesar_registro"},{"method":"POST","route":"logout","handler":"\\App\\Controllers\\Usuario::logout"},{"method":"POST","route":"perfil\/actualizar-datos","handler":"\\App\\Controllers\\UserProfile::actualizar_datos"},{"method":"POST","route":"add-to-wishlist","handler":"\\App\\Controllers\\UserProfile::add_to_wishlist"},{"method":"POST","route":"juego\/([0-9]+)\/guardar-resena","handler":"\\App\\Controllers\\Juegos::guardarResena"},{"method":"POST","route":"votar-util\/([0-9]+)","handler":"\\App\\Controllers\\Juegos::votarUtil\/$1"},{"method":"POST","route":"perfil\/subir-foto","handler":"\\App\\Controllers\\Admin_controllers\\Admin::subir_foto"},{"method":"POST","route":"perfil\/banear-usuario\/([0-9]+)","handler":"\\App\\Controllers\\Admin_controllers\\Admin::banear_usuario\/$1"},{"method":"POST","route":"perfil\/desbanear-usuario\/([0-9]+)","handler":"\\App\\Controllers\\Admin_controllers\\Admin::desbanear_usuario\/$1"},{"method":"POST","route":"perfil\/guardar-categoria","handler":"\\App\\Controllers\\Admin_controllers\\Admin::agregar_categoria"},{"method":"POST","route":"perfil\/eliminar-categoria\/([0-9]+)","handler":"\\App\\Controllers\\Admin_controllers\\Admin::eliminar_categoria\/$1"},{"method":"POST","route":"perfil\/guardar-juego","handler":"\\App\\Controllers\\Admin_controllers\\Admin::subir_juego"},{"method":"POST","route":"perfil\/actualizar-juego\/([0-9]+)","handler":"\\App\\Controllers\\Admin_controllers\\Admin::actualizar_juego\/$1"},{"method":"POST","route":"perfil\/desactivar-juego\/([0-9]+)","handler":"\\App\\Controllers\\Admin_controllers\\Admin::desactivar_juego\/$1"},{"method":"POST","route":"perfil\/activar-juego\/([0-9]+)","handler":"\\App\\Controllers\\Admin_controllers\\Admin::activar_juego\/$1"}]},"badgeValue":17,"isEmpty":false,"hasTabContent":true,"hasLabel":false,"icon":"data:image\/png;base64,iVBORw0KGgoAAAANSUhEUgAAABgAAAAYCAYAAADgdz34AAAAAXNSR0IArs4c6QAAAARnQU1BAACxjwv8YQUAAAAJcEhZcwAADsMAAA7DAcdvqGQAAAFDSURBVEhL7ZRNSsNQFIUjVXSiOFEcuQIHDpzpxC0IGYeE\/BEInbWlCHEDLsSiuANdhKDjgm6ggtSJ+l25ldrmmTwIgtgDh\/t37r1J+16cX0dRFMtpmu5pWAkrvYjjOB7AETzStBFW+inxu3KUJMmhludQpoflS1zXban4LYqiO224h6VLTHr8Z+z8EpIHFF9gG78nDVmW7UgTHKjsCyY98QP+pcq+g8Ku2s8G8X3f3\/I8b038WZTp+bO38zxfFd+I6YY6sNUvFlSDk9CRhiAI1jX1I9Cfw7GG1UB8LAuwbU0ZwQnbRDeEN5qqBxZMLtE1ti9LtbREnMIuOXnyIf5rGIb7Wq8HmlZgwYBH7ORTcKH5E4mpjeGt9fBZcHE2GCQ3Vt7oTNPNg+FXLHnSsHkw\/FR+Gg2bB8Ptzrst\/v6C\/wrH+QB+duli6MYJdQAAAABJRU5ErkJggg==","hasTimelineData":false,"timelineData":[]},{"title":"Events","titleSafe":"events","titleDetails":"","display":{"events":{"pre_system":{"event":"pre_system","duration":"5.80","count":1},"dbquery":{"event":"dbquery","duration":"0.20","count":17}}},"badgeValue":18,"isEmpty":false,"hasTabContent":true,"hasLabel":false,"icon":"data:image\/png;base64,iVBORw0KGgoAAAANSUhEUgAAABgAAAAYCAYAAADgdz34AAAAAXNSR0IArs4c6QAAAARnQU1BAACxjwv8YQUAAAAJcEhZcwAADsMAAA7DAcdvqGQAAAEASURBVEhL7ZXNDcIwDIVTsRBH1uDQDdquUA6IM1xgCA6MwJUN2hk6AQzAz0vl0ETUxC5VT3zSU5w81\/mRMGZysixbFEVR0jSKNt8geQU9aRpFmp\/keX6AbjZ5oB74vsaN5lSzA4tLSjpBFxsjeSuRy4d2mDdQTWU7YLbXTNN05mKyovj5KL6B7q3hoy3KwdZxBlT+Ipz+jPHrBqOIynZgcZonoukb\/0ckiTHqNvDXtXEAaygRbaB9FvUTjRUHsIYS0QaSp+Dw6wT4hiTmYHOcYZsdLQ2CbXa4ftuuYR4x9vYZgdb4vsFYUdmABMYeukK9\/SUme3KMFQ77+Yfzh8eYF8+orDuDWU5LAAAAAElFTkSuQmCC","hasTimelineData":true,"timelineData":[{"name":"Event: pre_system","component":"Events","start":1749941889.945409,"duration":0.005800008773803711},{"name":"Event: dbquery","component":"Events","start":1749941889.973259,"duration":1.5974044799804688e-5},{"name":"Event: dbquery","component":"Events","start":1749941889.975577,"duration":8.821487426757812e-6},{"name":"Event: dbquery","component":"Events","start":1749941889.977867,"duration":9.059906005859375e-6},{"name":"Event: dbquery","component":"Events","start":1749941889.980332,"duration":1.0013580322265625e-5},{"name":"Event: dbquery","component":"Events","start":1749941889.982588,"duration":7.867813110351562e-6},{"name":"Event: dbquery","component":"Events","start":1749941889.984823,"duration":1.3113021850585938e-5},{"name":"Event: dbquery","component":"Events","start":1749941889.987074,"duration":1.811981201171875e-5},{"name":"Event: dbquery","component":"Events","start":1749941889.989489,"duration":8.821487426757812e-6},{"name":"Event: dbquery","component":"Events","start":1749941889.991774,"duration":8.821487426757812e-6},{"name":"Event: dbquery","component":"Events","start":1749941889.994503,"duration":1.0013580322265625e-5},{"name":"Event: dbquery","component":"Events","start":1749941889.996983,"duration":2.288818359375e-5},{"name":"Event: dbquery","component":"Events","start":1749941889.999299,"duration":9.059906005859375e-6},{"name":"Event: dbquery","component":"Events","start":1749941890.001537,"duration":1.0013580322265625e-5},{"name":"Event: dbquery","component":"Events","start":1749941890.003903,"duration":9.059906005859375e-6},{"name":"Event: dbquery","component":"Events","start":1749941890.006552,"duration":1.811981201171875e-5},{"name":"Event: dbquery","component":"Events","start":1749941890.008825,"duration":8.821487426757812e-6},{"name":"Event: dbquery","component":"Events","start":1749941890.011114,"duration":1.2159347534179688e-5}]}],"vars":{"varData":{"View Data":[]},"session":{"__ci_last_regenerate":"<pre>1749941822<\/pre>","_ci_previous_url":"http:\/\/kings.local\/perfil","user_id":"4","email":"francomontecino2003@hotmail.com","nickname":"frann17","is_active":"1","is_admin":"1","user_img":"1749100889_4d62dcd9c1dfab820f39.jpg","exito-msg":"Juego actualizado correctamente","__ci_vars":"<pre>Array\n(\n    [exito-msg] =&gt; new\n)\n<\/pre>"},"post":{"title":"Cyberpunk 2077","price":"29.99","release_date":"2020-12-10","developer":"CD Projekt RED","about":"Un RPG de mundo abierto ambientado en un futuro dist\u00f3pico lleno de acci\u00f3n, tecnolog\u00eda y decisiones.","synopsis":"Cyberpunk 2077 transporta a los jugadores a Night City, una metr\u00f3polis obsesionada con el poder, la modificaci\u00f3n corporal y el estatus. Interpret\u00e1s a V, un mercenario en busca de un implante que puede otorgar la inmortalidad.\r\n\r\nA pesar de un lanzamiento pol\u00e9mico, el juego se ha pulido con el tiempo y ofrece una experiencia profunda, con una narrativa no lineal, m\u00faltiples finales y una ambientaci\u00f3n vibrante que da vida a un mundo cyberpunk como nunca antes.","categories":"<pre>Array\n(\n    [0] =&gt; 1\n    [1] =&gt; 2\n    [2] =&gt; 7\n    [3] =&gt; 9\n    [4] =&gt; 10\n    [5] =&gt; 11\n)\n<\/pre>","game_rating":"8.0","trailer":"8X2kIfS6fb8?si=pwOQQLVDsxTOdGv4","cover_url":"https:\/\/cdn2.steamgriddb.com\/grid\/f39b781760a403dedaa05587e8889c1a.png","card_url":"https:\/\/cdn2.steamgriddb.com\/grid\/796c4dde50f3fcea641e99ab0fb6dc70.jpg","banner_url":"https:\/\/cdn2.steamgriddb.com\/hero\/fb87582825f9d28a8d42c5e5e5e8b23d.png","logo_url":"https:\/\/cdn2.steamgriddb.com\/logo\/2b2e7393b05b5b52af65bf2ed7f4ad4f.png","additional_images":"<pre>Array\n(\n    [0] =&gt; https:\/\/shared.fastly.steamstatic.com\/store_item_assets\/steam\/apps\/1091500\/ss_7924f64b6e5d586a80418c9896a1c92881a7905b.1920x1080.jpg?t=1746519355\n    [1] =&gt; https:\/\/shared.fastly.steamstatic.com\/store_item_assets\/steam\/apps\/1091500\/ss_b529b0abc43f55fc23fe8058eddb6e37c9629a6a.1920x1080.jpg?t=1746519355\n    [2] =&gt; https:\/\/shared.fastly.steamstatic.com\/store_item_assets\/steam\/apps\/1091500\/ss_4eb068b1cf52c91b57157b84bed18a186ed7714b.1920x1080.jpg?t=1746519355\n    [3] =&gt; https:\/\/shared.fastly.steamstatic.com\/store_item_assets\/steam\/apps\/1091500\/ss_8640d9db74f7cad714f6ecfb0e1aceaa3f887e58.1920x1080.jpg?t=1746519355\n)\n<\/pre>","min_cpu":"Intel Core i5-3570K \/ AMD FX-8310","min_ram":"8 GB","min_gpu":"GTX 780 \/ RX 470","min_storage":"70 GB HDD","rec_cpu":"Intel Core i7-12700 \/ AMD Ryzen 7 7800X3D","rec_ram":"16 GB","rec_gpu":"RTX 3060 \/ RX 6700 XT","rec_storage":"70 GB SSD","ultra_cpu":"Intel Core i9-13900K \/ AMD Ryzen 9 7950X3D","ultra_ram":"32 GB","ultra_gpu":"RTX 4090 \/ RX 7900 XTX","ultra_storage":"70 GB SSD"},"headers":{"Content-Type":"application\/x-www-form-urlencoded","Host":"kings.local","User-Agent":"Mozilla\/5.0 (Windows NT 10.0; Win64; x64; rv:139.0) Gecko\/20100101 Firefox\/139.0","Accept":"text\/html,application\/xhtml+xml,application\/xml;q=0.9,*\/*;q=0.8","Accept-Language":"es-AR,es;q=0.8,en-US;q=0.5,en;q=0.3","Accept-Encoding":"gzip, deflate","Origin":"http:\/\/kings.local","Connection":"keep-alive","Referer":"http:\/\/kings.local\/perfil","Cookie":"ci_session=64e521bf47f773cb623b59c20777cc02; csrf_cookie_name=47bb66a40fe2e8ba12ff8c74fd208ebd","Upgrade-Insecure-Requests":"1","Dnt":"1","Sec-Gpc":"1","Priority":"u=0, i"},"cookies":{"ci_session":"64e521bf47f773cb623b59c20777cc02","csrf_cookie_name":"47bb66a40fe2e8ba12ff8c74fd208ebd"},"request":"HTTP\/1.1","response":{"statusCode":303,"reason":"See Other","contentType":"text\/html; charset=UTF-8","headers":{"Cache-Control":"no-store, max-age=0, no-cache","Content-Type":"text\/html; charset=UTF-8","Location":"http:\/\/kings.local\/perfil"}}},"config":{"ciVersion":"4.6.0","phpVersion":"8.2.12","phpSAPI":"apache2handler","environment":"development","baseURL":"http:\/\/kings.local\/","timezone":"UTC","locale":"en","cspEnabled":false}}